{
  "start_city": "Glendora",
  "start_state": "CA",
  "start_lat_lon": {
    "lat": 34.1360095,
    "lon": -117.8653377
  },
  "end_city": "San Dimas",
  "end_state": "CA",
  "end_lat_lon": {
    "lat": 34.1066655,
    "lon": -117.8067257
  },
  "total_length_mi": 5.1,
  "legs": [
    {
      "start_lat_lon": {
        "lat": 34.13601,
        "lon": -117.86534
      },
      "leg_dist_mi": 0.06859302023507069,
      "cum_dist_mi": 0.0
    },
    {
      "start_lat_lon": {
        "lat": 34.13603,
        "lon": -117.86414
      },
      "leg_dist_mi": 0.057153426195216295,
      "cum_dist_mi": 0.06859302023507069
    },
    {
      "start_lat_lon": {
        "lat": 34.13604,
        "lon": -117.86314
      },
      "leg_dist_mi": 0.09315584520711546,
      "cum_dist_mi": 0.12574644643028698
    },
    {
      "start_lat_lon": {
        "lat": 34.13603,
        "lon": -117.86151
      },
      "leg_dist_mi": 0.16973469308580347,
      "cum_dist_mi": 0.21890229163740244
    },
    {
      "start_lat_lon": {
        "lat": 34.13604,
        "lon": -117.85854
      },
      "leg_dist_mi": 0.20345599969325184,
      "cum_dist_mi": 0.3886369847232059
    },
    {
      "start_lat_lon": {
        "lat": 34.13606,
        "lon": -117.85498
      },
      "leg_dist_mi": 0.26688782142914136,
      "cum_dist_mi": 0.5920929844164577
    },
    {
      "start_lat_lon": {
        "lat": 34.13607,
        "lon": -117.85031
      },
      "leg_dist_mi": 0.16230527733822328,
      "cum_dist_mi": 0.8589808058455991
    },
    {
      "start_lat_lon": {
        "lat": 34.13608,
        "lon": -117.84747
      },
      "leg_dist_mi": 0.04458173985119523,
      "cum_dist_mi": 1.0212860831838224
    },
    {
      "start_lat_lon": {
        "lat": 34.13609,
        "lon": -117.84669
      },
      "leg_dist_mi": 0.02057371858192856,
      "cum_dist_mi": 1.0658678230350176
    },
    {
      "start_lat_lon": {
        "lat": 34.13609,
        "lon": -117.84633
      },
      "leg_dist_mi": 0.0076164457290845205,
      "cum_dist_mi": 1.0864415416169462
    },
    {
      "start_lat_lon": {
        "lat": 34.13598,
        "lon": -117.84632
      },
      "leg_dist_mi": 0.012428140537551258,
      "cum_dist_mi": 1.0940579873460308
    },
    {
      "start_lat_lon": {
        "lat": 34.1358,
        "lon": -117.84632
      },
      "leg_dist_mi": 0.017270764366036553,
      "cum_dist_mi": 1.106486127883582
    },
    {
      "start_lat_lon": {
        "lat": 34.13555,
        "lon": -117.84633
      },
      "leg_dist_mi": 0.1194496067824092,
      "cum_dist_mi": 1.1237568922496186
    },
    {
      "start_lat_lon": {
        "lat": 34.13382,
        "lon": -117.84634
      },
      "leg_dist_mi": 0.15880504638215426,
      "cum_dist_mi": 1.2432064990320277
    },
    {
      "start_lat_lon": {
        "lat": 34.13152,
        "lon": -117.84635
      },
      "leg_dist_mi": 0.1836683023533678,
      "cum_dist_mi": 1.402011545414182
    },
    {
      "start_lat_lon": {
        "lat": 34.12886,
        "lon": -117.84638
      },
      "leg_dist_mi": 0.007616449397883298,
      "cum_dist_mi": 1.5856798477675498
    },
    {
      "start_lat_lon": {
        "lat": 34.12875,
        "lon": -117.84639
      },
      "leg_dist_mi": 0.005715418137770099,
      "cum_dist_mi": 1.593296297165433
    },
    {
      "start_lat_lon": {
        "lat": 34.12875,
        "lon": -117.84629
      },
      "leg_dist_mi": 0.06286959952244096,
      "cum_dist_mi": 1.599011715303203
    },
    {
      "start_lat_lon": {
        "lat": 34.12875,
        "lon": -117.84519
      },
      "leg_dist_mi": 0.12516955415517736,
      "cum_dist_mi": 1.661881314825644
    },
    {
      "start_lat_lon": {
        "lat": 34.12876,
        "lon": -117.843
      },
      "leg_dist_mi": 0.13946300631849512,
      "cum_dist_mi": 1.7870508689808213
    },
    {
      "start_lat_lon": {
        "lat": 34.12878,
        "lon": -117.84056
      },
      "leg_dist_mi": 0.049728910677635636,
      "cum_dist_mi": 1.9265138752993165
    },
    {
      "start_lat_lon": {
        "lat": 34.12879,
        "lon": -117.83969
      },
      "leg_dist_mi": 0.0315558682713633,
      "cum_dist_mi": 1.9762427859769522
    },
    {
      "start_lat_lon": {
        "lat": 34.12883,
        "lon": -117.83914
      },
      "leg_dist_mi": 0.03389718129317565,
      "cum_dist_mi": 2.0077986542483157
    },
    {
      "start_lat_lon": {
        "lat": 34.12888,
        "lon": -117.83855
      },
      "leg_dist_mi": 0.03887091390474788,
      "cum_dist_mi": 2.0416958355414914
    },
    {
      "start_lat_lon": {
        "lat": 34.12889,
        "lon": -117.83787
      },
      "leg_dist_mi": 0.04932676809413781,
      "cum_dist_mi": 2.0805667494462394
    },
    {
      "start_lat_lon": {
        "lat": 34.12895,
        "lon": -117.83701
      },
      "leg_dist_mi": 0.0664746012979809,
      "cum_dist_mi": 2.1298935175403773
    },
    {
      "start_lat_lon": {
        "lat": 34.12902,
        "lon": -117.83585
      },
      "leg_dist_mi": 0.07266760764162618,
      "cum_dist_mi": 2.1963681188383584
    },
    {
      "start_lat_lon": {
        "lat": 34.12907,
        "lon": -117.83458
      },
      "leg_dist_mi": 0.04063213942391727,
      "cum_dist_mi": 2.2690357264799847
    },
    {
      "start_lat_lon": {
        "lat": 34.1291,
        "lon": -117.83387
      },
      "leg_dist_mi": 0.032073171040502536,
      "cum_dist_mi": 2.309667865903902
    },
    {
      "start_lat_lon": {
        "lat": 34.12907,
        "lon": -117.83331
      },
      "leg_dist_mi": 0.04177378767890285,
      "cum_dist_mi": 2.3417410369444047
    },
    {
      "start_lat_lon": {
        "lat": 34.12904,
        "lon": -117.83258
      },
      "leg_dist_mi": 0.03794844500254546,
      "cum_dist_mi": 2.3835148246233078
    },
    {
      "start_lat_lon": {
        "lat": 34.12898,
        "lon": -117.83192
      },
      "leg_dist_mi": 0.03778631026879031,
      "cum_dist_mi": 2.4214632696258533
    },
    {
      "start_lat_lon": {
        "lat": 34.12888,
        "lon": -117.83127
      },
      "leg_dist_mi": 0.039179367202006016,
      "cum_dist_mi": 2.4592495798946437
    },
    {
      "start_lat_lon": {
        "lat": 34.12876,
        "lon": -117.8306
      },
      "leg_dist_mi": 0.04016109774050873,
      "cum_dist_mi": 2.4984289470966496
    },
    {
      "start_lat_lon": {
        "lat": 34.12865,
        "lon": -117.82991
      },
      "leg_dist_mi": 0.08703151588311994,
      "cum_dist_mi": 2.5385900448371586
    },
    {
      "start_lat_lon": {
        "lat": 34.12839,
        "lon": -117.82842
      },
      "leg_dist_mi": 0.11151764835990359,
      "cum_dist_mi": 2.6256215607202784
    },
    {
      "start_lat_lon": {
        "lat": 34.12806,
        "lon": -117.82651
      },
      "leg_dist_mi": 0.09082448880034517,
      "cum_dist_mi": 2.737139209080182
    },
    {
      "start_lat_lon": {
        "lat": 34.12777,
        "lon": -117.82496
      },
      "leg_dist_mi": 0.09305609893322676,
      "cum_dist_mi": 2.827963697880527
    },
    {
      "start_lat_lon": {
        "lat": 34.12748,
        "lon": -117.82337
      },
      "leg_dist_mi": 0.03973879562817009,
      "cum_dist_mi": 2.921019796813754
    },
    {
      "start_lat_lon": {
        "lat": 34.12736,
        "lon": -117.82269
      },
      "leg_dist_mi": 0.04072312098891742,
      "cum_dist_mi": 2.960758592441924
    },
    {
      "start_lat_lon": {
        "lat": 34.12725,
        "lon": -117.82199
      },
      "leg_dist_mi": 0.06898421995092763,
      "cum_dist_mi": 3.0014817134308416
    },
    {
      "start_lat_lon": {
        "lat": 34.12704,
        "lon": -117.82081
      },
      "leg_dist_mi": 0.05149566914967703,
      "cum_dist_mi": 3.070465933381769
    },
    {
      "start_lat_lon": {
        "lat": 34.12688,
        "lon": -117.81993
      },
      "leg_dist_mi": 0.012316294505375459,
      "cum_dist_mi": 3.1219616025314463
    },
    {
      "start_lat_lon": {
        "lat": 34.12684,
        "lon": -117.81972
      },
      "leg_dist_mi": 0.004006345924053666,
      "cum_dist_mi": 3.1342778970368217
    },
    {
      "start_lat_lon": {
        "lat": 34.12687,
        "lon": -117.81966
      },
      "leg_dist_mi": 0.0017926503392180003,
      "cum_dist_mi": 3.1382842429608755
    },
    {
      "start_lat_lon": {
        "lat": 34.12689,
        "lon": -117.81964
      },
      "leg_dist_mi": 0.03624116092637536,
      "cum_dist_mi": 3.1400768933000935
    },
    {
      "start_lat_lon": {
        "lat": 34.12678,
        "lon": -117.81902
      },
      "leg_dist_mi": 0.026865514718872455,
      "cum_dist_mi": 3.176318054226469
    },
    {
      "start_lat_lon": {
        "lat": 34.1267,
        "lon": -117.81856
      },
      "leg_dist_mi": 0.013992604818292976,
      "cum_dist_mi": 3.203183568945341
    },
    {
      "start_lat_lon": {
        "lat": 34.12666,
        "lon": -117.81832
      },
      "leg_dist_mi": 0.10760643699145925,
      "cum_dist_mi": 3.217176173763634
    },
    {
      "start_lat_lon": {
        "lat": 34.12633,
        "lon": -117.81648
      },
      "leg_dist_mi": 0.169596327184113,
      "cum_dist_mi": 3.324782610755093
    },
    {
      "start_lat_lon": {
        "lat": 34.12581,
        "lon": -117.81358
      },
      "leg_dist_mi": 0.013786813088137168,
      "cum_dist_mi": 3.494378937939206
    },
    {
      "start_lat_lon": {
        "lat": 34.12579,
        "lon": -117.81334
      },
      "leg_dist_mi": 0.012183718726941104,
      "cum_dist_mi": 3.5081657510273434
    },
    {
      "start_lat_lon": {
        "lat": 34.12571,
        "lon": -117.81315
      },
      "leg_dist_mi": 0.008507151844672697,
      "cum_dist_mi": 3.5203494697542843
    },
    {
      "start_lat_lon": {
        "lat": 34.12565,
        "lon": -117.81302
      },
      "leg_dist_mi": 0.059469324236439705,
      "cum_dist_mi": 3.528856621598957
    },
    {
      "start_lat_lon": {
        "lat": 34.12548,
        "lon": -117.812
      },
      "leg_dist_mi": 0.11334139280472572,
      "cum_dist_mi": 3.588325945835397
    },
    {
      "start_lat_lon": {
        "lat": 34.12514,
        "lon": -117.81006
      },
      "leg_dist_mi": 0.13615073033835126,
      "cum_dist_mi": 3.7016673386401227
    },
    {
      "start_lat_lon": {
        "lat": 34.12473,
        "lon": -117.80773
      },
      "leg_dist_mi": 0.03218562125740882,
      "cum_dist_mi": 3.837818068978474
    },
    {
      "start_lat_lon": {
        "lat": 34.12463,
        "lon": -117.80718
      },
      "leg_dist_mi": 0.010372543697653534,
      "cum_dist_mi": 3.8700036902358828
    },
    {
      "start_lat_lon": {
        "lat": 34.12448,
        "lon": -117.80717
      },
      "leg_dist_mi": 0.02485628107554172,
      "cum_dist_mi": 3.880376233933536
    },
    {
      "start_lat_lon": {
        "lat": 34.12412,
        "lon": -117.80717
      },
      "leg_dist_mi": 0.10563919456918569,
      "cum_dist_mi": 3.905232515009078
    },
    {
      "start_lat_lon": {
        "lat": 34.12259,
        "lon": -117.80717
      },
      "leg_dist_mi": 0.09804588593471546,
      "cum_dist_mi": 4.0108717095782636
    },
    {
      "start_lat_lon": {
        "lat": 34.12117,
        "lon": -117.80718
      },
      "leg_dist_mi": 0.08494293751029727,
      "cum_dist_mi": 4.108917595512979
    },
    {
      "start_lat_lon": {
        "lat": 34.11994,
        "lon": -117.80721
      },
      "leg_dist_mi": 0.05800925507064777,
      "cum_dist_mi": 4.193860533023277
    },
    {
      "start_lat_lon": {
        "lat": 34.1191,
        "lon": -117.80719
      },
      "leg_dist_mi": 0.00836392499524515,
      "cum_dist_mi": 4.2518697880939245
    },
    {
      "start_lat_lon": {
        "lat": 34.11898,
        "lon": -117.80717
      },
      "leg_dist_mi": 0.0052847099335607125,
      "cum_dist_mi": 4.260233713089169
    },
    {
      "start_lat_lon": {
        "lat": 34.11893,
        "lon": -117.8071
      },
      "leg_dist_mi": 0.009666331529694538,
      "cum_dist_mi": 4.26551842302273
    },
    {
      "start_lat_lon": {
        "lat": 34.11879,
        "lon": -117.8071
      },
      "leg_dist_mi": 0.026243411470143304,
      "cum_dist_mi": 4.275184754552424
    },
    {
      "start_lat_lon": {
        "lat": 34.11841,
        "lon": -117.80711
      },
      "leg_dist_mi": 0.0020713567561121415,
      "cum_dist_mi": 4.301428166022568
    },
    {
      "start_lat_lon": {
        "lat": 34.11838,
        "lon": -117.80711
      },
      "leg_dist_mi": 0.0050329499927346255,
      "cum_dist_mi": 4.303499522778679
    },
    {
      "start_lat_lon": {
        "lat": 34.11832,
        "lon": -117.80716
      },
      "leg_dist_mi": 0.004181963190643622,
      "cum_dist_mi": 4.3085324727714145
    },
    {
      "start_lat_lon": {
        "lat": 34.11826,
        "lon": -117.80717
      },
      "leg_dist_mi": 0.010356783780999912,
      "cum_dist_mi": 4.312714435962058
    },
    {
      "start_lat_lon": {
        "lat": 34.11811,
        "lon": -117.80717
      },
      "leg_dist_mi": 0.08425262837950943,
      "cum_dist_mi": 4.323071219743058
    },
    {
      "start_lat_lon": {
        "lat": 34.11689,
        "lon": -117.8072
      },
      "leg_dist_mi": 0.024165828822918733,
      "cum_dist_mi": 4.407323848122568
    },
    {
      "start_lat_lon": {
        "lat": 34.11654,
        "lon": -117.8072
      },
      "leg_dist_mi": 0.05938164507970797,
      "cum_dist_mi": 4.431489676945486
    },
    {
      "start_lat_lon": {
        "lat": 34.11568,
        "lon": -117.80719
      },
      "leg_dist_mi": 0.08423711433620854,
      "cum_dist_mi": 4.490871322025194
    },
    {
      "start_lat_lon": {
        "lat": 34.11446,
        "lon": -117.8072
      },
      "leg_dist_mi": 0.03728442161309298,
      "cum_dist_mi": 4.575108436361403
    },
    {
      "start_lat_lon": {
        "lat": 34.11392,
        "lon": -117.8072
      },
      "leg_dist_mi": 0.007097786210447407,
      "cum_dist_mi": 4.612392857974497
    },
    {
      "start_lat_lon": {
        "lat": 34.11383,
        "lon": -117.80714
      },
      "leg_dist_mi": 0.017960857761631477,
      "cum_dist_mi": 4.619490644184944
    },
    {
      "start_lat_lon": {
        "lat": 34.11357,
        "lon": -117.80713
      },
      "leg_dist_mi": 0.03245125584824571,
      "cum_dist_mi": 4.637451501946575
    },
    {
      "start_lat_lon": {
        "lat": 34.1131,
        "lon": -117.80713
      },
      "leg_dist_mi": 0.033851472724646066,
      "cum_dist_mi": 4.669902757794821
    },
    {
      "start_lat_lon": {
        "lat": 34.11261,
        "lon": -117.80711
      },
      "leg_dist_mi": 0.08147537121947696,
      "cum_dist_mi": 4.7037542305194675
    },
    {
      "start_lat_lon": {
        "lat": 34.11143,
        "lon": -117.8071
      },
      "leg_dist_mi": 0.07457103444423757,
      "cum_dist_mi": 4.785229601738944
    },
    {
      "start_lat_lon": {
        "lat": 34.11035,
        "lon": -117.80711
      },
      "leg_dist_mi": 0.1636371837451569,
      "cum_dist_mi": 4.859800636183182
    },
    {
      "start_lat_lon": {
        "lat": 34.10798,
        "lon": -117.80711
      },
      "leg_dist_mi": 0.0904655036780386,
      "cum_dist_mi": 5.023437819928338
    },
    {
      "start_lat_lon": {
        "lat": 34.10667,
        "lon": -117.80714
      },
      "leg_dist_mi": 0.023439333298094868,
      "cum_dist_mi": 5.113903323606377
    },
    {
      "start_lat_lon": {
        "lat": 34.10667,
        "lon": -117.80673
      },
      "leg_dist_mi": 0.0,
      "cum_dist_mi": 5.137342656904472
    }
  ]
}