{
  "start_city": "Leavenworth",
  "start_state": "WA 98826",
  "start_lat_lon": {
    "lat": 47.59617069999999,
    "lon": -120.6614105
  },
  "end_city": "Stevens Pass",
  "end_state": "Washington 98826",
  "end_lat_lon": {
    "lat": 47.74606319999999,
    "lon": -121.0865441
  },
  "total_length_mi": 35.3,
  "legs": [
    {
      "start_lat_lon": {
        "lat": 47.59617,
        "lon": -120.66141
      },
      "leg_dist_mi": 0.3197701621399375,
      "cum_dist_mi": 0.0
    },
    {
      "start_lat_lon": {
        "lat": 47.5933,
        "lon": -120.6668
      },
      "leg_dist_mi": 0.11885238990446857,
      "cum_dist_mi": 0.3197701621399375
    },
    {
      "start_lat_lon": {
        "lat": 47.5921,
        "lon": -120.66863
      },
      "leg_dist_mi": 0.21865532965415393,
      "cum_dist_mi": 0.43862255204440603
    },
    {
      "start_lat_lon": {
        "lat": 47.58993,
        "lon": -120.67205
      },
      "leg_dist_mi": 0.1549046349605631,
      "cum_dist_mi": 0.6572778816985599
    },
    {
      "start_lat_lon": {
        "lat": 47.58874,
        "lon": -120.67487
      },
      "leg_dist_mi": 0.021400170364165395,
      "cum_dist_mi": 0.812182516659123
    },
    {
      "start_lat_lon": {
        "lat": 47.5886,
        "lon": -120.67528
      },
      "leg_dist_mi": 0.007377085063499854,
      "cum_dist_mi": 0.8335826870232884
    },
    {
      "start_lat_lon": {
        "lat": 47.58855,
        "lon": -120.67542
      },
      "leg_dist_mi": 0.07413069641574392,
      "cum_dist_mi": 0.8409597720867883
    },
    {
      "start_lat_lon": {
        "lat": 47.58794,
        "lon": -120.67673
      },
      "leg_dist_mi": 0.0858754323659213,
      "cum_dist_mi": 0.9150904685025322
    },
    {
      "start_lat_lon": {
        "lat": 47.58731,
        "lon": -120.67832
      },
      "leg_dist_mi": 0.029877736314835344,
      "cum_dist_mi": 1.0009659008684535
    },
    {
      "start_lat_lon": {
        "lat": 47.58714,
        "lon": -120.67891
      },
      "leg_dist_mi": 0.045970515293950805,
      "cum_dist_mi": 1.0308436371832888
    },
    {
      "start_lat_lon": {
        "lat": 47.58706,
        "lon": -120.67989
      },
      "leg_dist_mi": 0.06681797705373871,
      "cum_dist_mi": 1.0768141524772397
    },
    {
      "start_lat_lon": {
        "lat": 47.5873,
        "lon": -120.68128
      },
      "leg_dist_mi": 0.09393297503401896,
      "cum_dist_mi": 1.1436321295309784
    },
    {
      "start_lat_lon": {
        "lat": 47.58781,
        "lon": -120.68315
      },
      "leg_dist_mi": 0.03517096802117149,
      "cum_dist_mi": 1.2375651045649974
    },
    {
      "start_lat_lon": {
        "lat": 47.58787,
        "lon": -120.6839
      },
      "leg_dist_mi": 0.03730999649442231,
      "cum_dist_mi": 1.272736072586169
    },
    {
      "start_lat_lon": {
        "lat": 47.58778,
        "lon": -120.68469
      },
      "leg_dist_mi": 0.032212950188508095,
      "cum_dist_mi": 1.3100460690805913
    },
    {
      "start_lat_lon": {
        "lat": 47.58756,
        "lon": -120.6853
      },
      "leg_dist_mi": 0.08821038852894943,
      "cum_dist_mi": 1.3422590192690993
    },
    {
      "start_lat_lon": {
        "lat": 47.58673,
        "lon": -120.68674
      },
      "leg_dist_mi": 0.10852566173355378,
      "cum_dist_mi": 1.4304694077980487
    },
    {
      "start_lat_lon": {
        "lat": 47.58614,
        "lon": -120.6889
      },
      "leg_dist_mi": 0.2011301780902392,
      "cum_dist_mi": 1.5389950695316024
    },
    {
      "start_lat_lon": {
        "lat": 47.58482,
        "lon": -120.69275
      },
      "leg_dist_mi": 0.12468796711467975,
      "cum_dist_mi": 1.7401252476218416
    },
    {
      "start_lat_lon": {
        "lat": 47.58421,
        "lon": -120.69527
      },
      "leg_dist_mi": 0.0632593405020136,
      "cum_dist_mi": 1.8648132147365213
    },
    {
      "start_lat_lon": {
        "lat": 47.58406,
        "lon": -120.69661
      },
      "leg_dist_mi": 0.2123706860780169,
      "cum_dist_mi": 1.928072555238535
    },
    {
      "start_lat_lon": {
        "lat": 47.58408,
        "lon": -120.70117
      },
      "leg_dist_mi": 0.03665550283665192,
      "cum_dist_mi": 2.140443241316552
    },
    {
      "start_lat_lon": {
        "lat": 47.58419,
        "lon": -120.70194
      },
      "leg_dist_mi": 0.05849856145875867,
      "cum_dist_mi": 2.177098744153204
    },
    {
      "start_lat_lon": {
        "lat": 47.58456,
        "lon": -120.70307
      },
      "leg_dist_mi": 0.11776549686602918,
      "cum_dist_mi": 2.2355973056119627
    },
    {
      "start_lat_lon": {
        "lat": 47.58553,
        "lon": -120.70515
      },
      "leg_dist_mi": 0.04447795999871255,
      "cum_dist_mi": 2.353362802477992
    },
    {
      "start_lat_lon": {
        "lat": 47.58602,
        "lon": -120.70577
      },
      "leg_dist_mi": 0.07000280139875775,
      "cum_dist_mi": 2.3978407624767044
    },
    {
      "start_lat_lon": {
        "lat": 47.58691,
        "lon": -120.70649
      },
      "leg_dist_mi": 0.02967956466573832,
      "cum_dist_mi": 2.467843563875462
    },
    {
      "start_lat_lon": {
        "lat": 47.58726,
        "lon": -120.70686
      },
      "leg_dist_mi": 0.0659713598671922,
      "cum_dist_mi": 2.4975231285412005
    },
    {
      "start_lat_lon": {
        "lat": 47.58793,
        "lon": -120.70787
      },
      "leg_dist_mi": 0.07266220605617363,
      "cum_dist_mi": 2.563494488408393
    },
    {
      "start_lat_lon": {
        "lat": 47.58878,
        "lon": -120.70879
      },
      "leg_dist_mi": 0.12617125987213346,
      "cum_dist_mi": 2.6361566944645665
    },
    {
      "start_lat_lon": {
        "lat": 47.59045,
        "lon": -120.70989
      },
      "leg_dist_mi": 0.09995692169319943,
      "cum_dist_mi": 2.7623279543367
    },
    {
      "start_lat_lon": {
        "lat": 47.59184,
        "lon": -120.71049
      },
      "leg_dist_mi": 0.059033435123223725,
      "cum_dist_mi": 2.862284876029899
    },
    {
      "start_lat_lon": {
        "lat": 47.59257,
        "lon": -120.71115
      },
      "leg_dist_mi": 0.06386575247493634,
      "cum_dist_mi": 2.9213183111531227
    },
    {
      "start_lat_lon": {
        "lat": 47.59334,
        "lon": -120.71191
      },
      "leg_dist_mi": 0.060699496055751055,
      "cum_dist_mi": 2.985184063628059
    },
    {
      "start_lat_lon": {
        "lat": 47.59416,
        "lon": -120.71238
      },
      "leg_dist_mi": 0.1284588447992249,
      "cum_dist_mi": 3.0458835596838103
    },
    {
      "start_lat_lon": {
        "lat": 47.59593,
        "lon": -120.71323
      },
      "leg_dist_mi": 0.08445236376119356,
      "cum_dist_mi": 3.1743424044830353
    },
    {
      "start_lat_lon": {
        "lat": 47.59715,
        "lon": -120.71336
      },
      "leg_dist_mi": 0.11670129173754201,
      "cum_dist_mi": 3.2587947682442286
    },
    {
      "start_lat_lon": {
        "lat": 47.59884,
        "lon": -120.7134
      },
      "leg_dist_mi": 0.05706280773411967,
      "cum_dist_mi": 3.3754960599817707
    },
    {
      "start_lat_lon": {
        "lat": 47.59963,
        "lon": -120.71376
      },
      "leg_dist_mi": 0.06651887359149469,
      "cum_dist_mi": 3.4325588677158905
    },
    {
      "start_lat_lon": {
        "lat": 47.60045,
        "lon": -120.71451
      },
      "leg_dist_mi": 0.07661316507829279,
      "cum_dist_mi": 3.499077741307385
    },
    {
      "start_lat_lon": {
        "lat": 47.60137,
        "lon": -120.71543
      },
      "leg_dist_mi": 0.053294064770947384,
      "cum_dist_mi": 3.575690906385678
    },
    {
      "start_lat_lon": {
        "lat": 47.60213,
        "lon": -120.71563
      },
      "leg_dist_mi": 0.0881859308084896,
      "cum_dist_mi": 3.6289849711566253
    },
    {
      "start_lat_lon": {
        "lat": 47.60339,
        "lon": -120.71532
      },
      "leg_dist_mi": 0.0535628326182878,
      "cum_dist_mi": 3.717170901965115
    },
    {
      "start_lat_lon": {
        "lat": 47.60416,
        "lon": -120.71546
      },
      "leg_dist_mi": 0.07756553257129133,
      "cum_dist_mi": 3.770733734583403
    },
    {
      "start_lat_lon": {
        "lat": 47.6052,
        "lon": -120.71609
      },
      "leg_dist_mi": 0.09610785283499763,
      "cum_dist_mi": 3.8482992671546943
    },
    {
      "start_lat_lon": {
        "lat": 47.60658,
        "lon": -120.71636
      },
      "leg_dist_mi": 0.03831915348705218,
      "cum_dist_mi": 3.944407119989692
    },
    {
      "start_lat_lon": {
        "lat": 47.60712,
        "lon": -120.71655
      },
      "leg_dist_mi": 0.09281646177661568,
      "cum_dist_mi": 3.9827262734767443
    },
    {
      "start_lat_lon": {
        "lat": 47.60836,
        "lon": -120.71732
      },
      "leg_dist_mi": 0.1528632126713655,
      "cum_dist_mi": 4.07554273525336
    },
    {
      "start_lat_lon": {
        "lat": 47.61046,
        "lon": -120.71836
      },
      "leg_dist_mi": 0.1512264351259846,
      "cum_dist_mi": 4.228405947924726
    },
    {
      "start_lat_lon": {
        "lat": 47.61261,
        "lon": -120.71898
      },
      "leg_dist_mi": 0.09826818888288999,
      "cum_dist_mi": 4.37963238305071
    },
    {
      "start_lat_lon": {
        "lat": 47.61401,
        "lon": -120.71936
      },
      "leg_dist_mi": 0.03562864150678623,
      "cum_dist_mi": 4.4779005719336
    },
    {
      "start_lat_lon": {
        "lat": 47.6145,
        "lon": -120.7196
      },
      "leg_dist_mi": 0.1003497990587436,
      "cum_dist_mi": 4.513529213440386
    },
    {
      "start_lat_lon": {
        "lat": 47.61575,
        "lon": -120.7207
      },
      "leg_dist_mi": 0.03328331714199144,
      "cum_dist_mi": 4.61387901249913
    },
    {
      "start_lat_lon": {
        "lat": 47.61613,
        "lon": -120.72114
      },
      "leg_dist_mi": 0.10033634858737685,
      "cum_dist_mi": 4.647162329641121
    },
    {
      "start_lat_lon": {
        "lat": 47.61714,
        "lon": -120.72269
      },
      "leg_dist_mi": 0.03798724428079276,
      "cum_dist_mi": 4.7474986782284985
    },
    {
      "start_lat_lon": {
        "lat": 47.61758,
        "lon": -120.72318
      },
      "leg_dist_mi": 0.0745038142108401,
      "cum_dist_mi": 4.785485922509292
    },
    {
      "start_lat_lon": {
        "lat": 47.61856,
        "lon": -120.72385
      },
      "leg_dist_mi": 0.040441542296959815,
      "cum_dist_mi": 4.859989736720132
    },
    {
      "start_lat_lon": {
        "lat": 47.61913,
        "lon": -120.72405
      },
      "leg_dist_mi": 0.1653269668419038,
      "cum_dist_mi": 4.900431279017091
    },
    {
      "start_lat_lon": {
        "lat": 47.62151,
        "lon": -120.72444
      },
      "leg_dist_mi": 0.05847661483590242,
      "cum_dist_mi": 5.065758245858995
    },
    {
      "start_lat_lon": {
        "lat": 47.62234,
        "lon": -120.72469
      },
      "leg_dist_mi": 0.10345184806303498,
      "cum_dist_mi": 5.124234860694898
    },
    {
      "start_lat_lon": {
        "lat": 47.62379,
        "lon": -120.72525
      },
      "leg_dist_mi": 0.05470628540697819,
      "cum_dist_mi": 5.227686708757933
    },
    {
      "start_lat_lon": {
        "lat": 47.62458,
        "lon": -120.72534
      },
      "leg_dist_mi": 0.08717601945746752,
      "cum_dist_mi": 5.282392994164911
    },
    {
      "start_lat_lon": {
        "lat": 47.62584,
        "lon": -120.72546
      },
      "leg_dist_mi": 0.029799173798780065,
      "cum_dist_mi": 5.369569013622378
    },
    {
      "start_lat_lon": {
        "lat": 47.62625,
        "lon": -120.72566
      },
      "leg_dist_mi": 0.1305097926859862,
      "cum_dist_mi": 5.3993681874211585
    },
    {
      "start_lat_lon": {
        "lat": 47.62798,
        "lon": -120.72679
      },
      "leg_dist_mi": 0.17562706758633334,
      "cum_dist_mi": 5.529877980107145
    },
    {
      "start_lat_lon": {
        "lat": 47.63044,
        "lon": -120.72775
      },
      "leg_dist_mi": 0.03746977944568159,
      "cum_dist_mi": 5.705505047693478
    },
    {
      "start_lat_lon": {
        "lat": 47.63098,
        "lon": -120.72783
      },
      "leg_dist_mi": 0.04323618244137494,
      "cum_dist_mi": 5.74297482713916
    },
    {
      "start_lat_lon": {
        "lat": 47.63159,
        "lon": -120.72762
      },
      "leg_dist_mi": 0.06974773890439637,
      "cum_dist_mi": 5.786211009580535
    },
    {
      "start_lat_lon": {
        "lat": 47.63244,
        "lon": -120.72681
      },
      "leg_dist_mi": 0.06531675574250409,
      "cum_dist_mi": 5.855958748484932
    },
    {
      "start_lat_lon": {
        "lat": 47.63326,
        "lon": -120.72611
      },
      "leg_dist_mi": 0.09551985702686325,
      "cum_dist_mi": 5.921275504227436
    },
    {
      "start_lat_lon": {
        "lat": 47.63457,
        "lon": -120.72545
      },
      "leg_dist_mi": 0.11217340263241865,
      "cum_dist_mi": 6.0167953612542995
    },
    {
      "start_lat_lon": {
        "lat": 47.63614,
        "lon": -120.72483
      },
      "leg_dist_mi": 0.06186591678865687,
      "cum_dist_mi": 6.128968763886718
    },
    {
      "start_lat_lon": {
        "lat": 47.63691,
        "lon": -120.72415
      },
      "leg_dist_mi": 0.04564654700221567,
      "cum_dist_mi": 6.1908346806753745
    },
    {
      "start_lat_lon": {
        "lat": 47.63738,
        "lon": -120.72346
      },
      "leg_dist_mi": 0.08411425077586866,
      "cum_dist_mi": 6.23648122767759
    },
    {
      "start_lat_lon": {
        "lat": 47.63805,
        "lon": -120.72195
      },
      "leg_dist_mi": 0.07641582114193665,
      "cum_dist_mi": 6.320595478453459
    },
    {
      "start_lat_lon": {
        "lat": 47.63876,
        "lon": -120.72069
      },
      "leg_dist_mi": 0.049327541384952656,
      "cum_dist_mi": 6.397011299595396
    },
    {
      "start_lat_lon": {
        "lat": 47.63939,
        "lon": -120.72019
      },
      "leg_dist_mi": 0.055257283243544,
      "cum_dist_mi": 6.446338840980348
    },
    {
      "start_lat_lon": {
        "lat": 47.64018,
        "lon": -120.72
      },
      "leg_dist_mi": 0.024326499163335447,
      "cum_dist_mi": 6.501596124223893
    },
    {
      "start_lat_lon": {
        "lat": 47.64053,
        "lon": -120.72006
      },
      "leg_dist_mi": 0.09796221345526533,
      "cum_dist_mi": 6.5259226233872285
    },
    {
      "start_lat_lon": {
        "lat": 47.64189,
        "lon": -120.72066
      },
      "leg_dist_mi": 0.09548314927732093,
      "cum_dist_mi": 6.623884836842493
    },
    {
      "start_lat_lon": {
        "lat": 47.64319,
        "lon": -120.72136
      },
      "leg_dist_mi": 0.08844474471656813,
      "cum_dist_mi": 6.719367986119814
    },
    {
      "start_lat_lon": {
        "lat": 47.64423,
        "lon": -120.72247
      },
      "leg_dist_mi": 0.08147873566394571,
      "cum_dist_mi": 6.807812730836383
    },
    {
      "start_lat_lon": {
        "lat": 47.64523,
        "lon": -120.7234
      },
      "leg_dist_mi": 0.03909787389171294,
      "cum_dist_mi": 6.889291466500328
    },
    {
      "start_lat_lon": {
        "lat": 47.64578,
        "lon": -120.7236
      },
      "leg_dist_mi": 0.09285792273730158,
      "cum_dist_mi": 6.928389340392041
    },
    {
      "start_lat_lon": {
        "lat": 47.64712,
        "lon": -120.72377
      },
      "leg_dist_mi": 0.1933467737950125,
      "cum_dist_mi": 7.021247263129342
    },
    {
      "start_lat_lon": {
        "lat": 47.64992,
        "lon": -120.72383
      },
      "leg_dist_mi": 0.06381509755344193,
      "cum_dist_mi": 7.214594036924354
    },
    {
      "start_lat_lon": {
        "lat": 47.65083,
        "lon": -120.72407
      },
      "leg_dist_mi": 0.0478570082845012,
      "cum_dist_mi": 7.278409134477796
    },
    {
      "start_lat_lon": {
        "lat": 47.65145,
        "lon": -120.72453
      },
      "leg_dist_mi": 0.028567444427630175,
      "cum_dist_mi": 7.3262661427622975
    },
    {
      "start_lat_lon": {
        "lat": 47.65179,
        "lon": -120.72488
      },
      "leg_dist_mi": 0.08326738664136403,
      "cum_dist_mi": 7.354833587189928
    },
    {
      "start_lat_lon": {
        "lat": 47.65264,
        "lon": -120.72615
      },
      "leg_dist_mi": 0.18293285966529566,
      "cum_dist_mi": 7.438100973831292
    },
    {
      "start_lat_lon": {
        "lat": 47.65448,
        "lon": -120.72898
      },
      "leg_dist_mi": 0.04999718910416602,
      "cum_dist_mi": 7.621033833496588
    },
    {
      "start_lat_lon": {
        "lat": 47.65511,
        "lon": -120.72951
      },
      "leg_dist_mi": 0.04940281345237229,
      "cum_dist_mi": 7.671031022600754
    },
    {
      "start_lat_lon": {
        "lat": 47.65581,
        "lon": -120.72973
      },
      "leg_dist_mi": 0.03729602219477427,
      "cum_dist_mi": 7.720433836053126
    },
    {
      "start_lat_lon": {
        "lat": 47.65635,
        "lon": -120.72971
      },
      "leg_dist_mi": 0.05992114900771296,
      "cum_dist_mi": 7.757729858247901
    },
    {
      "start_lat_lon": {
        "lat": 47.6572,
        "lon": -120.72945
      },
      "leg_dist_mi": 0.11362680643859026,
      "cum_dist_mi": 7.817651007255614
    },
    {
      "start_lat_lon": {
        "lat": 47.65882,
        "lon": -120.72902
      },
      "leg_dist_mi": 0.05847496288852169,
      "cum_dist_mi": 7.931277813694204
    },
    {
      "start_lat_lon": {
        "lat": 47.65965,
        "lon": -120.72927
      },
      "leg_dist_mi": 0.1410122722486865,
      "cum_dist_mi": 7.989752776582725
    },
    {
      "start_lat_lon": {
        "lat": 47.66144,
        "lon": -120.73073
      },
      "leg_dist_mi": 0.06995225817952336,
      "cum_dist_mi": 8.130765048831412
    },
    {
      "start_lat_lon": {
        "lat": 47.66222,
        "lon": -120.73169
      },
      "leg_dist_mi": 0.06423343372627922,
      "cum_dist_mi": 8.200717307010935
    },
    {
      "start_lat_lon": {
        "lat": 47.6628,
        "lon": -120.73277
      },
      "leg_dist_mi": 0.1303650908770508,
      "cum_dist_mi": 8.264950740737214
    },
    {
      "start_lat_lon": {
        "lat": 47.66386,
        "lon": -120.73509
      },
      "leg_dist_mi": 0.06770303525091417,
      "cum_dist_mi": 8.395315831614266
    },
    {
      "start_lat_lon": {
        "lat": 47.66462,
        "lon": -120.73601
      },
      "leg_dist_mi": 0.06593341824591792,
      "cum_dist_mi": 8.46301886686518
    },
    {
      "start_lat_lon": {
        "lat": 47.66554,
        "lon": -120.73639
      },
      "leg_dist_mi": 0.11945638460813696,
      "cum_dist_mi": 8.528952285111098
    },
    {
      "start_lat_lon": {
        "lat": 47.66727,
        "lon": -120.73636
      },
      "leg_dist_mi": 0.06466176745155164,
      "cum_dist_mi": 8.648408669719235
    },
    {
      "start_lat_lon": {
        "lat": 47.66819,
        "lon": -120.7361
      },
      "leg_dist_mi": 0.25075248246092224,
      "cum_dist_mi": 8.713070437170787
    },
    {
      "start_lat_lon": {
        "lat": 47.67176,
        "lon": -120.73511
      },
      "leg_dist_mi": 0.10407169408882641,
      "cum_dist_mi": 8.96382291963171
    },
    {
      "start_lat_lon": {
        "lat": 47.67326,
        "lon": -120.73489
      },
      "leg_dist_mi": 0.04337236257532406,
      "cum_dist_mi": 9.067894613720537
    },
    {
      "start_lat_lon": {
        "lat": 47.67388,
        "lon": -120.73474
      },
      "leg_dist_mi": 0.056975610736164355,
      "cum_dist_mi": 9.11126697629586
    },
    {
      "start_lat_lon": {
        "lat": 47.67466,
        "lon": -120.73434
      },
      "leg_dist_mi": 0.08622483634302203,
      "cum_dist_mi": 9.168242587032026
    },
    {
      "start_lat_lon": {
        "lat": 47.6759,
        "lon": -120.73412
      },
      "leg_dist_mi": 0.07665288892989518,
      "cum_dist_mi": 9.254467423375047
    },
    {
      "start_lat_lon": {
        "lat": 47.67701,
        "lon": -120.73415
      },
      "leg_dist_mi": 0.14772611839346833,
      "cum_dist_mi": 9.331120312304941
    },
    {
      "start_lat_lon": {
        "lat": 47.67914,
        "lon": -120.73445
      },
      "leg_dist_mi": 0.19796116786487528,
      "cum_dist_mi": 9.47884643069841
    },
    {
      "start_lat_lon": {
        "lat": 47.682,
        "lon": -120.73475
      },
      "leg_dist_mi": 0.11672389553892745,
      "cum_dist_mi": 9.676807598563284
    },
    {
      "start_lat_lon": {
        "lat": 47.68368,
        "lon": -120.73503
      },
      "leg_dist_mi": 0.14155544752225552,
      "cum_dist_mi": 9.793531494102211
    },
    {
      "start_lat_lon": {
        "lat": 47.68569,
        "lon": -120.73563
      },
      "leg_dist_mi": 0.10544988981569754,
      "cum_dist_mi": 9.935086941624467
    },
    {
      "start_lat_lon": {
        "lat": 47.68717,
        "lon": -120.73619
      },
      "leg_dist_mi": 0.20828172997031047,
      "cum_dist_mi": 10.040536831440164
    },
    {
      "start_lat_lon": {
        "lat": 47.69004,
        "lon": -120.73757
      },
      "leg_dist_mi": 0.12033683896066791,
      "cum_dist_mi": 10.248818561410475
    },
    {
      "start_lat_lon": {
        "lat": 47.69157,
        "lon": -120.73881
      },
      "leg_dist_mi": 0.08012125556999934,
      "cum_dist_mi": 10.369155400371143
    },
    {
      "start_lat_lon": {
        "lat": 47.69252,
        "lon": -120.7398
      },
      "leg_dist_mi": 0.07835378882555288,
      "cum_dist_mi": 10.449276655941143
    },
    {
      "start_lat_lon": {
        "lat": 47.69338,
        "lon": -120.7409
      },
      "leg_dist_mi": 0.22153761172908737,
      "cum_dist_mi": 10.527630444766695
    },
    {
      "start_lat_lon": {
        "lat": 47.69558,
        "lon": -120.74437
      },
      "leg_dist_mi": 0.0903404338594721,
      "cum_dist_mi": 10.749168056495781
    },
    {
      "start_lat_lon": {
        "lat": 47.69671,
        "lon": -120.74535
      },
      "leg_dist_mi": 0.05480148643788648,
      "cum_dist_mi": 10.839508490355254
    },
    {
      "start_lat_lon": {
        "lat": 47.69747,
        "lon": -120.74569
      },
      "leg_dist_mi": 0.05615975346597198,
      "cum_dist_mi": 10.89430997679314
    },
    {
      "start_lat_lon": {
        "lat": 47.69828,
        "lon": -120.7458
      },
      "leg_dist_mi": 0.21656804506085564,
      "cum_dist_mi": 10.950469730259112
    },
    {
      "start_lat_lon": {
        "lat": 47.70138,
        "lon": -120.74509
      },
      "leg_dist_mi": 0.21814387271516603,
      "cum_dist_mi": 11.167037775319967
    },
    {
      "start_lat_lon": {
        "lat": 47.70441,
        "lon": -120.74376
      },
      "leg_dist_mi": 0.2990121093492608,
      "cum_dist_mi": 11.385181648035132
    },
    {
      "start_lat_lon": {
        "lat": 47.70865,
        "lon": -120.74245
      },
      "leg_dist_mi": 0.16835509106989352,
      "cum_dist_mi": 11.684193757384394
    },
    {
      "start_lat_lon": {
        "lat": 47.71105,
        "lon": -120.74181
      },
      "leg_dist_mi": 0.09071110582660358,
      "cum_dist_mi": 11.852548848454287
    },
    {
      "start_lat_lon": {
        "lat": 47.71233,
        "lon": -120.74137
      },
      "leg_dist_mi": 0.4609715540859318,
      "cum_dist_mi": 11.94325995428089
    },
    {
      "start_lat_lon": {
        "lat": 47.71867,
        "lon": -120.73826
      },
      "leg_dist_mi": 0.21419074521178835,
      "cum_dist_mi": 12.404231508366822
    },
    {
      "start_lat_lon": {
        "lat": 47.72163,
        "lon": -120.73688
      },
      "leg_dist_mi": 0.20622606709522467,
      "cum_dist_mi": 12.61842225357861
    },
    {
      "start_lat_lon": {
        "lat": 47.72461,
        "lon": -120.73658
      },
      "leg_dist_mi": 0.08354601354648775,
      "cum_dist_mi": 12.824648320673834
    },
    {
      "start_lat_lon": {
        "lat": 47.72582,
        "lon": -120.73657
      },
      "leg_dist_mi": 0.07707806603999043,
      "cum_dist_mi": 12.908194334220322
    },
    {
      "start_lat_lon": {
        "lat": 47.7269,
        "lon": -120.73699
      },
      "leg_dist_mi": 0.042296182929838895,
      "cum_dist_mi": 12.985272400260312
    },
    {
      "start_lat_lon": {
        "lat": 47.72744,
        "lon": -120.73742
      },
      "leg_dist_mi": 0.0883438732110602,
      "cum_dist_mi": 13.02756858319015
    },
    {
      "start_lat_lon": {
        "lat": 47.72852,
        "lon": -120.73844
      },
      "leg_dist_mi": 0.07621490452448589,
      "cum_dist_mi": 13.115912456401212
    },
    {
      "start_lat_lon": {
        "lat": 47.72956,
        "lon": -120.73899
      },
      "leg_dist_mi": 0.06464056827441166,
      "cum_dist_mi": 13.192127360925697
    },
    {
      "start_lat_lon": {
        "lat": 47.73049,
        "lon": -120.73915
      },
      "leg_dist_mi": 0.07397174964038297,
      "cum_dist_mi": 13.256767929200109
    },
    {
      "start_lat_lon": {
        "lat": 47.73156,
        "lon": -120.73907
      },
      "leg_dist_mi": 0.2145110386334238,
      "cum_dist_mi": 13.330739678840493
    },
    {
      "start_lat_lon": {
        "lat": 47.73465,
        "lon": -120.73859
      },
      "leg_dist_mi": 0.1792035545218581,
      "cum_dist_mi": 13.545250717473916
    },
    {
      "start_lat_lon": {
        "lat": 47.73724,
        "lon": -120.73834
      },
      "leg_dist_mi": 0.27740228571715053,
      "cum_dist_mi": 13.724454271995775
    },
    {
      "start_lat_lon": {
        "lat": 47.74124,
        "lon": -120.73778
      },
      "leg_dist_mi": 0.6719742950013632,
      "cum_dist_mi": 14.001856557712925
    },
    {
      "start_lat_lon": {
        "lat": 47.75097,
        "lon": -120.73746
      },
      "leg_dist_mi": 0.11546334506190005,
      "cum_dist_mi": 14.673830852714287
    },
    {
      "start_lat_lon": {
        "lat": 47.75264,
        "lon": -120.73759
      },
      "leg_dist_mi": 0.07797952199070665,
      "cum_dist_mi": 14.789294197776188
    },
    {
      "start_lat_lon": {
        "lat": 47.75375,
        "lon": -120.7379
      },
      "leg_dist_mi": 0.10496233516040994,
      "cum_dist_mi": 14.867273719766894
    },
    {
      "start_lat_lon": {
        "lat": 47.75521,
        "lon": -120.73853
      },
      "leg_dist_mi": 0.10214492970876735,
      "cum_dist_mi": 14.972236054927304
    },
    {
      "start_lat_lon": {
        "lat": 47.75656,
        "lon": -120.73943
      },
      "leg_dist_mi": 0.3839384639020725,
      "cum_dist_mi": 15.074380984636072
    },
    {
      "start_lat_lon": {
        "lat": 47.76153,
        "lon": -120.74314
      },
      "leg_dist_mi": 0.07468764639530387,
      "cum_dist_mi": 15.458319448538145
    },
    {
      "start_lat_lon": {
        "lat": 47.76244,
        "lon": -120.74401
      },
      "leg_dist_mi": 0.0671710851463486,
      "cum_dist_mi": 15.533007094933449
    },
    {
      "start_lat_lon": {
        "lat": 47.76308,
        "lon": -120.7451
      },
      "leg_dist_mi": 0.04434974165532925,
      "cum_dist_mi": 15.600178180079798
    },
    {
      "start_lat_lon": {
        "lat": 47.76336,
        "lon": -120.74596
      },
      "leg_dist_mi": 0.07538735760584298,
      "cum_dist_mi": 15.644527921735127
    },
    {
      "start_lat_lon": {
        "lat": 47.76364,
        "lon": -120.74753
      },
      "leg_dist_mi": 0.1765567516219958,
      "cum_dist_mi": 15.71991527934097
    },
    {
      "start_lat_lon": {
        "lat": 47.76407,
        "lon": -120.75128
      },
      "leg_dist_mi": 0.29143571875850843,
      "cum_dist_mi": 15.896472030962967
    },
    {
      "start_lat_lon": {
        "lat": 47.76478,
        "lon": -120.75747
      },
      "leg_dist_mi": 0.2000087743153644,
      "cum_dist_mi": 16.187907749721475
    },
    {
      "start_lat_lon": {
        "lat": 47.76526,
        "lon": -120.76172
      },
      "leg_dist_mi": 0.17556303357886707,
      "cum_dist_mi": 16.38791652403684
    },
    {
      "start_lat_lon": {
        "lat": 47.76582,
        "lon": -120.76541
      },
      "leg_dist_mi": 0.13449066855317987,
      "cum_dist_mi": 16.563479557615707
    },
    {
      "start_lat_lon": {
        "lat": 47.76637,
        "lon": -120.76819
      },
      "leg_dist_mi": 0.10406163938885477,
      "cum_dist_mi": 16.697970226168888
    },
    {
      "start_lat_lon": {
        "lat": 47.76688,
        "lon": -120.7703
      },
      "leg_dist_mi": 0.09073682961766769,
      "cum_dist_mi": 16.802031865557744
    },
    {
      "start_lat_lon": {
        "lat": 47.76719,
        "lon": -120.7722
      },
      "leg_dist_mi": 0.06792835222563753,
      "cum_dist_mi": 16.892768695175413
    },
    {
      "start_lat_lon": {
        "lat": 47.76726,
        "lon": -120.77366
      },
      "leg_dist_mi": 0.08363151077180948,
      "cum_dist_mi": 16.96069704740105
    },
    {
      "start_lat_lon": {
        "lat": 47.76712,
        "lon": -120.77545
      },
      "leg_dist_mi": 0.1042582505257934,
      "cum_dist_mi": 17.04432855817286
    },
    {
      "start_lat_lon": {
        "lat": 47.76664,
        "lon": -120.77758
      },
      "leg_dist_mi": 0.32071340000562504,
      "cum_dist_mi": 17.148586808698653
    },
    {
      "start_lat_lon": {
        "lat": 47.76447,
        "lon": -120.78369
      },
      "leg_dist_mi": 0.04026963375268963,
      "cum_dist_mi": 17.46930020870428
    },
    {
      "start_lat_lon": {
        "lat": 47.7643,
        "lon": -120.78452
      },
      "leg_dist_mi": 0.06533738907241447,
      "cum_dist_mi": 17.50956984245697
    },
    {
      "start_lat_lon": {
        "lat": 47.76415,
        "lon": -120.78591
      },
      "leg_dist_mi": 0.11544882574531183,
      "cum_dist_mi": 17.574907231529384
    },
    {
      "start_lat_lon": {
        "lat": 47.76428,
        "lon": -120.78839
      },
      "leg_dist_mi": 0.041413999095150845,
      "cum_dist_mi": 17.690356057274695
    },
    {
      "start_lat_lon": {
        "lat": 47.76444,
        "lon": -120.78925
      },
      "leg_dist_mi": 0.23136824802427663,
      "cum_dist_mi": 17.731770056369847
    },
    {
      "start_lat_lon": {
        "lat": 47.76591,
        "lon": -120.79373
      },
      "leg_dist_mi": 0.7260298470716869,
      "cum_dist_mi": 17.963138304394125
    },
    {
      "start_lat_lon": {
        "lat": 47.77067,
        "lon": -120.80768
      },
      "leg_dist_mi": 0.20264658406318586,
      "cum_dist_mi": 18.68916815146581
    },
    {
      "start_lat_lon": {
        "lat": 47.77208,
        "lon": -120.81151
      },
      "leg_dist_mi": 0.39025927576113334,
      "cum_dist_mi": 18.891814735528996
    },
    {
      "start_lat_lon": {
        "lat": 47.77499,
        "lon": -120.81872
      },
      "leg_dist_mi": 0.47810203179895194,
      "cum_dist_mi": 19.282074011290128
    },
    {
      "start_lat_lon": {
        "lat": 47.77857,
        "lon": -120.82754
      },
      "leg_dist_mi": 0.42323593945443755,
      "cum_dist_mi": 19.76017604308908
    },
    {
      "start_lat_lon": {
        "lat": 47.78135,
        "lon": -120.83567
      },
      "leg_dist_mi": 0.1494029097443554,
      "cum_dist_mi": 20.183411982543515
    },
    {
      "start_lat_lon": {
        "lat": 47.78237,
        "lon": -120.83851
      },
      "leg_dist_mi": 0.18648543429793057,
      "cum_dist_mi": 20.33281489228787
    },
    {
      "start_lat_lon": {
        "lat": 47.78371,
        "lon": -120.842
      },
      "leg_dist_mi": 0.4238996323607003,
      "cum_dist_mi": 20.519300326585803
    },
    {
      "start_lat_lon": {
        "lat": 47.78676,
        "lon": -120.84993
      },
      "leg_dist_mi": 0.07354980799463899,
      "cum_dist_mi": 20.943199958946504
    },
    {
      "start_lat_lon": {
        "lat": 47.78722,
        "lon": -120.85136
      },
      "leg_dist_mi": 0.05828320317110548,
      "cum_dist_mi": 21.016749766941142
    },
    {
      "start_lat_lon": {
        "lat": 47.78747,
        "lon": -120.85256
      },
      "leg_dist_mi": 0.11248904872510453,
      "cum_dist_mi": 21.075032970112247
    },
    {
      "start_lat_lon": {
        "lat": 47.78765,
        "lon": -120.85497
      },
      "leg_dist_mi": 0.0858661222869493,
      "cum_dist_mi": 21.187522018837353
    },
    {
      "start_lat_lon": {
        "lat": 47.78769,
        "lon": -120.85682
      },
      "leg_dist_mi": 0.05994210900117285,
      "cum_dist_mi": 21.2733881411243
    },
    {
      "start_lat_lon": {
        "lat": 47.78785,
        "lon": -120.85809
      },
      "leg_dist_mi": 0.09452890954047913,
      "cum_dist_mi": 21.333330250125474
    },
    {
      "start_lat_lon": {
        "lat": 47.78854,
        "lon": -120.85985
      },
      "leg_dist_mi": 0.1258981829128012,
      "cum_dist_mi": 21.427859159665953
    },
    {
      "start_lat_lon": {
        "lat": 47.78967,
        "lon": -120.86198
      },
      "leg_dist_mi": 0.09374044680573376,
      "cum_dist_mi": 21.553757342578756
    },
    {
      "start_lat_lon": {
        "lat": 47.79026,
        "lon": -120.8638
      },
      "leg_dist_mi": 0.097949419806235,
      "cum_dist_mi": 21.647497789384488
    },
    {
      "start_lat_lon": {
        "lat": 47.7906,
        "lon": -120.86585
      },
      "leg_dist_mi": 0.1749804556498362,
      "cum_dist_mi": 21.745447209190722
    },
    {
      "start_lat_lon": {
        "lat": 47.79102,
        "lon": -120.86957
      },
      "leg_dist_mi": 0.12740382311991102,
      "cum_dist_mi": 21.92042766484056
    },
    {
      "start_lat_lon": {
        "lat": 47.79132,
        "lon": -120.87228
      },
      "leg_dist_mi": 0.051953269350012495,
      "cum_dist_mi": 22.04783148796047
    },
    {
      "start_lat_lon": {
        "lat": 47.79132,
        "lon": -120.8734
      },
      "leg_dist_mi": 0.07705541604248856,
      "cum_dist_mi": 22.09978475731048
    },
    {
      "start_lat_lon": {
        "lat": 47.79102,
        "lon": -120.875
      },
      "leg_dist_mi": 0.21689749640512246,
      "cum_dist_mi": 22.176840173352968
    },
    {
      "start_lat_lon": {
        "lat": 47.78974,
        "lon": -120.87927
      },
      "leg_dist_mi": 0.05863549876332573,
      "cum_dist_mi": 22.39373766975809
    },
    {
      "start_lat_lon": {
        "lat": 47.78931,
        "lon": -120.88036
      },
      "leg_dist_mi": 0.061505463041903255,
      "cum_dist_mi": 22.452373168521415
    },
    {
      "start_lat_lon": {
        "lat": 47.78871,
        "lon": -120.88134
      },
      "leg_dist_mi": 0.08638297023413886,
      "cum_dist_mi": 22.51387863156332
    },
    {
      "start_lat_lon": {
        "lat": 47.78787,
        "lon": -120.88272
      },
      "leg_dist_mi": 0.0250966674772967,
      "cum_dist_mi": 22.60026160179746
    },
    {
      "start_lat_lon": {
        "lat": 47.78769,
        "lon": -120.88319
      },
      "leg_dist_mi": 0.03409344559767057,
      "cum_dist_mi": 22.625358269274756
    },
    {
      "start_lat_lon": {
        "lat": 47.78752,
        "lon": -120.88388
      },
      "leg_dist_mi": 0.06729775122455794,
      "cum_dist_mi": 22.659451714872425
    },
    {
      "start_lat_lon": {
        "lat": 47.78749,
        "lon": -120.88533
      },
      "leg_dist_mi": 0.1395358595021276,
      "cum_dist_mi": 22.726749466096983
    },
    {
      "start_lat_lon": {
        "lat": 47.78771,
        "lon": -120.88832
      },
      "leg_dist_mi": 0.04641060920247769,
      "cum_dist_mi": 22.86628532559911
    },
    {
      "start_lat_lon": {
        "lat": 47.78773,
        "lon": -120.88932
      },
      "leg_dist_mi": 0.038931751408307604,
      "cum_dist_mi": 22.91269593480159
    },
    {
      "start_lat_lon": {
        "lat": 47.78761,
        "lon": -120.89014
      },
      "leg_dist_mi": 0.05717857998029242,
      "cum_dist_mi": 22.951627686209896
    },
    {
      "start_lat_lon": {
        "lat": 47.78725,
        "lon": -120.89125
      },
      "leg_dist_mi": 0.03663782451412016,
      "cum_dist_mi": 23.008806266190188
    },
    {
      "start_lat_lon": {
        "lat": 47.78693,
        "lon": -120.89188
      },
      "leg_dist_mi": 0.07179698361184295,
      "cum_dist_mi": 23.045444090704308
    },
    {
      "start_lat_lon": {
        "lat": 47.78607,
        "lon": -120.89275
      },
      "leg_dist_mi": 0.12918593846142068,
      "cum_dist_mi": 23.11724107431615
    },
    {
      "start_lat_lon": {
        "lat": 47.78427,
        "lon": -120.89351
      },
      "leg_dist_mi": 0.037328621859736996,
      "cum_dist_mi": 23.246427012777573
    },
    {
      "start_lat_lon": {
        "lat": 47.78378,
        "lon": -120.89385
      },
      "leg_dist_mi": 0.03684736713617496,
      "cum_dist_mi": 23.28375563463731
    },
    {
      "start_lat_lon": {
        "lat": 47.78336,
        "lon": -120.89434
      },
      "leg_dist_mi": 0.027810427505734446,
      "cum_dist_mi": 23.320603001773485
    },
    {
      "start_lat_lon": {
        "lat": 47.78311,
        "lon": -120.89481
      },
      "leg_dist_mi": 0.06507305419324132,
      "cum_dist_mi": 23.34841342927922
    },
    {
      "start_lat_lon": {
        "lat": 47.78274,
        "lon": -120.8961
      },
      "leg_dist_mi": 0.046939787764303645,
      "cum_dist_mi": 23.41348648347246
    },
    {
      "start_lat_lon": {
        "lat": 47.7827,
        "lon": -120.89711
      },
      "leg_dist_mi": 0.1716726699074439,
      "cum_dist_mi": 23.460426271236766
    },
    {
      "start_lat_lon": {
        "lat": 47.78296,
        "lon": -120.90079
      },
      "leg_dist_mi": 0.07017782971727533,
      "cum_dist_mi": 23.63209894114421
    },
    {
      "start_lat_lon": {
        "lat": 47.7829,
        "lon": -120.9023
      },
      "leg_dist_mi": 0.0797517474988965,
      "cum_dist_mi": 23.702276770861484
    },
    {
      "start_lat_lon": {
        "lat": 47.7826,
        "lon": -120.90396
      },
      "leg_dist_mi": 0.17275344350531766,
      "cum_dist_mi": 23.78202851836038
    },
    {
      "start_lat_lon": {
        "lat": 47.78171,
        "lon": -120.90744
      },
      "leg_dist_mi": 0.06220585968664284,
      "cum_dist_mi": 23.9547819618657
    },
    {
      "start_lat_lon": {
        "lat": 47.78127,
        "lon": -120.90861
      },
      "leg_dist_mi": 0.06555800700939232,
      "cum_dist_mi": 24.01698782155234
    },
    {
      "start_lat_lon": {
        "lat": 47.78062,
        "lon": -120.90964
      },
      "leg_dist_mi": 0.05367644214075308,
      "cum_dist_mi": 24.082545828561734
    },
    {
      "start_lat_lon": {
        "lat": 47.7801,
        "lon": -120.9105
      },
      "leg_dist_mi": 0.060549567027923114,
      "cum_dist_mi": 24.136222270702486
    },
    {
      "start_lat_lon": {
        "lat": 47.77974,
        "lon": -120.91169
      },
      "leg_dist_mi": 0.060415082690184654,
      "cum_dist_mi": 24.19677183773041
    },
    {
      "start_lat_lon": {
        "lat": 47.77969,
        "lon": -120.91299
      },
      "leg_dist_mi": 0.050562260634306765,
      "cum_dist_mi": 24.257186920420594
    },
    {
      "start_lat_lon": {
        "lat": 47.77986,
        "lon": -120.91405
      },
      "leg_dist_mi": 0.17922523428709655,
      "cum_dist_mi": 24.307749181054902
    },
    {
      "start_lat_lon": {
        "lat": 47.78067,
        "lon": -120.91772
      },
      "leg_dist_mi": 0.11426489258153379,
      "cum_dist_mi": 24.486974415341997
    },
    {
      "start_lat_lon": {
        "lat": 47.78144,
        "lon": -120.9199
      },
      "leg_dist_mi": 0.19883142230379294,
      "cum_dist_mi": 24.60123930792353
    },
    {
      "start_lat_lon": {
        "lat": 47.78296,
        "lon": -120.92354
      },
      "leg_dist_mi": 0.08451871919899703,
      "cum_dist_mi": 24.800070730227326
    },
    {
      "start_lat_lon": {
        "lat": 47.7834,
        "lon": -120.92524
      },
      "leg_dist_mi": 0.08647434226129183,
      "cum_dist_mi": 24.884589449426322
    },
    {
      "start_lat_lon": {
        "lat": 47.7836,
        "lon": -120.92708
      },
      "leg_dist_mi": 0.07434553448395691,
      "cum_dist_mi": 24.971063791687612
    },
    {
      "start_lat_lon": {
        "lat": 47.78354,
        "lon": -120.92868
      },
      "leg_dist_mi": 0.09967598469690293,
      "cum_dist_mi": 25.04540932617157
    },
    {
      "start_lat_lon": {
        "lat": 47.78313,
        "lon": -120.93074
      },
      "leg_dist_mi": 0.1950845310716813,
      "cum_dist_mi": 25.14508531086847
    },
    {
      "start_lat_lon": {
        "lat": 47.78167,
        "lon": -120.93434
      },
      "leg_dist_mi": 0.061298197301109615,
      "cum_dist_mi": 25.340169841940153
    },
    {
      "start_lat_lon": {
        "lat": 47.78145,
        "lon": -120.93562
      },
      "leg_dist_mi": 0.062259919269006675,
      "cum_dist_mi": 25.401468039241262
    },
    {
      "start_lat_lon": {
        "lat": 47.78157,
        "lon": -120.93695
      },
      "leg_dist_mi": 0.10609158527108828,
      "cum_dist_mi": 25.46372795851027
    },
    {
      "start_lat_lon": {
        "lat": 47.78191,
        "lon": -120.93918
      },
      "leg_dist_mi": 0.039995396980677535,
      "cum_dist_mi": 25.569819543781357
    },
    {
      "start_lat_lon": {
        "lat": 47.78187,
        "lon": -120.94004
      },
      "leg_dist_mi": 0.03916738433203187,
      "cum_dist_mi": 25.609814940762035
    },
    {
      "start_lat_lon": {
        "lat": 47.78167,
        "lon": -120.94083
      },
      "leg_dist_mi": 0.0744881530461838,
      "cum_dist_mi": 25.648982325094067
    },
    {
      "start_lat_lon": {
        "lat": 47.78101,
        "lon": -120.9421
      },
      "leg_dist_mi": 0.3753012517124245,
      "cum_dist_mi": 25.72347047814025
    },
    {
      "start_lat_lon": {
        "lat": 47.77716,
        "lon": -120.94781
      },
      "leg_dist_mi": 0.0843403380732763,
      "cum_dist_mi": 26.098771729852675
    },
    {
      "start_lat_lon": {
        "lat": 47.77648,
        "lon": -120.94932
      },
      "leg_dist_mi": 0.10402407482337839,
      "cum_dist_mi": 26.18311206792595
    },
    {
      "start_lat_lon": {
        "lat": 47.77599,
        "lon": -120.95144
      },
      "leg_dist_mi": 0.09421587436936622,
      "cum_dist_mi": 26.28713614274933
    },
    {
      "start_lat_lon": {
        "lat": 47.77596,
        "lon": -120.95347
      },
      "leg_dist_mi": 0.07425374579016362,
      "cum_dist_mi": 26.381352017118694
    },
    {
      "start_lat_lon": {
        "lat": 47.77594,
        "lon": -120.95507
      },
      "leg_dist_mi": 0.06048158750436851,
      "cum_dist_mi": 26.455605762908856
    },
    {
      "start_lat_lon": {
        "lat": 47.77567,
        "lon": -120.95631
      },
      "leg_dist_mi": 0.07604944458627895,
      "cum_dist_mi": 26.516087350413226
    },
    {
      "start_lat_lon": {
        "lat": 47.77512,
        "lon": -120.95773
      },
      "leg_dist_mi": 0.08666907976344634,
      "cum_dist_mi": 26.592136794999504
    },
    {
      "start_lat_lon": {
        "lat": 47.7746,
        "lon": -120.95943
      },
      "leg_dist_mi": 0.05849741356851023,
      "cum_dist_mi": 26.67880587476295
    },
    {
      "start_lat_lon": {
        "lat": 47.77449,
        "lon": -120.96068
      },
      "leg_dist_mi": 0.09138940218071848,
      "cum_dist_mi": 26.73730328833146
    },
    {
      "start_lat_lon": {
        "lat": 47.77462,
        "lon": -120.96264
      },
      "leg_dist_mi": 0.06421651370735203,
      "cum_dist_mi": 26.82869269051218
    },
    {
      "start_lat_lon": {
        "lat": 47.77469,
        "lon": -120.96402
      },
      "leg_dist_mi": 0.045188497168859025,
      "cum_dist_mi": 26.89290920421953
    },
    {
      "start_lat_lon": {
        "lat": 47.77458,
        "lon": -120.96498
      },
      "leg_dist_mi": 0.030136855759694166,
      "cum_dist_mi": 26.93809770138839
    },
    {
      "start_lat_lon": {
        "lat": 47.77445,
        "lon": -120.9656
      },
      "leg_dist_mi": 0.12010948203906416,
      "cum_dist_mi": 26.968234557148083
    },
    {
      "start_lat_lon": {
        "lat": 47.77359,
        "lon": -120.96785
      },
      "leg_dist_mi": 0.04939962027428347,
      "cum_dist_mi": 27.08834403918715
    },
    {
      "start_lat_lon": {
        "lat": 47.77323,
        "lon": -120.96877
      },
      "leg_dist_mi": 0.16520222637856968,
      "cum_dist_mi": 27.13774365946143
    },
    {
      "start_lat_lon": {
        "lat": 47.77203,
        "lon": -120.97185
      },
      "leg_dist_mi": 0.1401096756511381,
      "cum_dist_mi": 27.30294588584
    },
    {
      "start_lat_lon": {
        "lat": 47.77136,
        "lon": -120.9747
      },
      "leg_dist_mi": 0.12963294268846678,
      "cum_dist_mi": 27.44305556149114
    },
    {
      "start_lat_lon": {
        "lat": 47.77107,
        "lon": -120.97746
      },
      "leg_dist_mi": 0.14711010540528668,
      "cum_dist_mi": 27.572688504179606
    },
    {
      "start_lat_lon": {
        "lat": 47.77105,
        "lon": -120.98063
      },
      "leg_dist_mi": 0.06809876541106458,
      "cum_dist_mi": 27.719798609584892
    },
    {
      "start_lat_lon": {
        "lat": 47.77086,
        "lon": -120.98207
      },
      "leg_dist_mi": 0.06624671706087519,
      "cum_dist_mi": 27.787897374995957
    },
    {
      "start_lat_lon": {
        "lat": 47.77033,
        "lon": -120.98326
      },
      "leg_dist_mi": 0.07743166843927936,
      "cum_dist_mi": 27.85414409205683
    },
    {
      "start_lat_lon": {
        "lat": 47.76939,
        "lon": -120.98417
      },
      "leg_dist_mi": 0.08532774290013956,
      "cum_dist_mi": 27.93157576049611
    },
    {
      "start_lat_lon": {
        "lat": 47.76832,
        "lon": -120.98509
      },
      "leg_dist_mi": 0.058410175815058245,
      "cum_dist_mi": 28.01690350339625
    },
    {
      "start_lat_lon": {
        "lat": 47.76769,
        "lon": -120.98593
      },
      "leg_dist_mi": 0.06626021812540103,
      "cum_dist_mi": 28.07531367921131
    },
    {
      "start_lat_lon": {
        "lat": 47.76717,
        "lon": -120.98713
      },
      "leg_dist_mi": 0.08490512510389896,
      "cum_dist_mi": 28.14157389733671
    },
    {
      "start_lat_lon": {
        "lat": 47.76695,
        "lon": -120.98893
      },
      "leg_dist_mi": 0.04958399668530776,
      "cum_dist_mi": 28.226479022440607
    },
    {
      "start_lat_lon": {
        "lat": 47.76704,
        "lon": -120.98999
      },
      "leg_dist_mi": 0.3105636708134001,
      "cum_dist_mi": 28.276063019125914
    },
    {
      "start_lat_lon": {
        "lat": 47.76863,
        "lon": -120.99625
      },
      "leg_dist_mi": 0.11182310114784352,
      "cum_dist_mi": 28.586626689939315
    },
    {
      "start_lat_lon": {
        "lat": 47.76932,
        "lon": -120.99843
      },
      "leg_dist_mi": 0.06769326529600282,
      "cum_dist_mi": 28.69844979108716
    },
    {
      "start_lat_lon": {
        "lat": 47.76994,
        "lon": -120.99956
      },
      "leg_dist_mi": 0.03130235233391702,
      "cum_dist_mi": 28.766143056383164
    },
    {
      "start_lat_lon": {
        "lat": 47.7703,
        "lon": -120.99997
      },
      "leg_dist_mi": 0.10885643855102242,
      "cum_dist_mi": 28.79744540871708
    },
    {
      "start_lat_lon": {
        "lat": 47.77157,
        "lon": -121.00136
      },
      "leg_dist_mi": 0.03940620368343432,
      "cum_dist_mi": 28.906301847268104
    },
    {
      "start_lat_lon": {
        "lat": 47.77196,
        "lon": -121.00198
      },
      "leg_dist_mi": 0.03697848260042252,
      "cum_dist_mi": 28.945708050951538
    },
    {
      "start_lat_lon": {
        "lat": 47.77232,
        "lon": -121.00257
      },
      "leg_dist_mi": 0.029427302027817903,
      "cum_dist_mi": 28.98268653355196
    },
    {
      "start_lat_lon": {
        "lat": 47.77252,
        "lon": -121.00313
      },
      "leg_dist_mi": 0.03917342086956201,
      "cum_dist_mi": 29.012113835579775
    },
    {
      "start_lat_lon": {
        "lat": 47.77272,
        "lon": -121.00392
      },
      "leg_dist_mi": 0.2148987698680508,
      "cum_dist_mi": 29.05128725644934
    },
    {
      "start_lat_lon": {
        "lat": 47.7733,
        "lon": -121.00847
      },
      "leg_dist_mi": 0.27805306525133533,
      "cum_dist_mi": 29.26618602631739
    },
    {
      "start_lat_lon": {
        "lat": 47.7745,
        "lon": -121.01419
      },
      "leg_dist_mi": 0.08641840826737456,
      "cum_dist_mi": 29.544239091568723
    },
    {
      "start_lat_lon": {
        "lat": 47.77498,
        "lon": -121.01591
      },
      "leg_dist_mi": 0.14937515170468077,
      "cum_dist_mi": 29.630657499836097
    },
    {
      "start_lat_lon": {
        "lat": 47.77596,
        "lon": -121.01878
      },
      "leg_dist_mi": 0.14871244220259963,
      "cum_dist_mi": 29.78003265154078
    },
    {
      "start_lat_lon": {
        "lat": 47.77702,
        "lon": -121.02157
      },
      "leg_dist_mi": 0.0738799103637712,
      "cum_dist_mi": 29.92874509374338
    },
    {
      "start_lat_lon": {
        "lat": 47.7778,
        "lon": -121.02266
      },
      "leg_dist_mi": 0.08294403049819246,
      "cum_dist_mi": 30.002625004107152
    },
    {
      "start_lat_lon": {
        "lat": 47.77883,
        "lon": -121.02358
      },
      "leg_dist_mi": 0.26532141562834033,
      "cum_dist_mi": 30.085569034605346
    },
    {
      "start_lat_lon": {
        "lat": 47.78213,
        "lon": -121.02651
      },
      "leg_dist_mi": 0.08119319774598842,
      "cum_dist_mi": 30.350890450233685
    },
    {
      "start_lat_lon": {
        "lat": 47.78305,
        "lon": -121.0276
      },
      "leg_dist_mi": 0.055257803117270285,
      "cum_dist_mi": 30.432083647979674
    },
    {
      "start_lat_lon": {
        "lat": 47.78355,
        "lon": -121.02853
      },
      "leg_dist_mi": 0.05950520310886112,
      "cum_dist_mi": 30.487341451096945
    },
    {
      "start_lat_lon": {
        "lat": 47.78397,
        "lon": -121.02965
      },
      "leg_dist_mi": 0.11505810562639335,
      "cum_dist_mi": 30.546846654205808
    },
    {
      "start_lat_lon": {
        "lat": 47.78439,
        "lon": -121.03205
      },
      "leg_dist_mi": 0.11736335793298043,
      "cum_dist_mi": 30.6619047598322
    },
    {
      "start_lat_lon": {
        "lat": 47.78465,
        "lon": -121.03455
      },
      "leg_dist_mi": 0.06730146369632171,
      "cum_dist_mi": 30.77926811776518
    },
    {
      "start_lat_lon": {
        "lat": 47.78462,
        "lon": -121.036
      },
      "leg_dist_mi": 0.05413487016942854,
      "cum_dist_mi": 30.8465695814615
    },
    {
      "start_lat_lon": {
        "lat": 47.7844,
        "lon": -121.03712
      },
      "leg_dist_mi": 0.12918120851531203,
      "cum_dist_mi": 30.90070445163093
    },
    {
      "start_lat_lon": {
        "lat": 47.78359,
        "lon": -121.03963
      },
      "leg_dist_mi": 0.0513048150460787,
      "cum_dist_mi": 31.029885660146242
    },
    {
      "start_lat_lon": {
        "lat": 47.78314,
        "lon": -121.04051
      },
      "leg_dist_mi": 0.09623177485752624,
      "cum_dist_mi": 31.081190475192322
    },
    {
      "start_lat_lon": {
        "lat": 47.78215,
        "lon": -121.04197
      },
      "leg_dist_mi": 0.0720952366050088,
      "cum_dist_mi": 31.177422250049847
    },
    {
      "start_lat_lon": {
        "lat": 47.78161,
        "lon": -121.0433
      },
      "leg_dist_mi": 0.24267225258279698,
      "cum_dist_mi": 31.249517486654856
    },
    {
      "start_lat_lon": {
        "lat": 47.78086,
        "lon": -121.04841
      },
      "leg_dist_mi": 0.06386574643574507,
      "cum_dist_mi": 31.492189739237652
    },
    {
      "start_lat_lon": {
        "lat": 47.78095,
        "lon": -121.04978
      },
      "leg_dist_mi": 0.1513158735803574,
      "cum_dist_mi": 31.556055485673397
    },
    {
      "start_lat_lon": {
        "lat": 47.78161,
        "lon": -121.05289
      },
      "leg_dist_mi": 0.04920210691242953,
      "cum_dist_mi": 31.707371359253756
    },
    {
      "start_lat_lon": {
        "lat": 47.78171,
        "lon": -121.05394
      },
      "leg_dist_mi": 0.05502458834121287,
      "cum_dist_mi": 31.756573466166184
    },
    {
      "start_lat_lon": {
        "lat": 47.78163,
        "lon": -121.05512
      },
      "leg_dist_mi": 0.1733345501324834,
      "cum_dist_mi": 31.811598054507396
    },
    {
      "start_lat_lon": {
        "lat": 47.78089,
        "lon": -121.05869
      },
      "leg_dist_mi": 0.11954607627424056,
      "cum_dist_mi": 31.98493260463988
    },
    {
      "start_lat_lon": {
        "lat": 47.78026,
        "lon": -121.06109
      },
      "leg_dist_mi": 0.054517509519323354,
      "cum_dist_mi": 32.10447868091412
    },
    {
      "start_lat_lon": {
        "lat": 47.77988,
        "lon": -121.06212
      },
      "leg_dist_mi": 0.16107736740969142,
      "cum_dist_mi": 32.15899619043344
    },
    {
      "start_lat_lon": {
        "lat": 47.77851,
        "lon": -121.06493
      },
      "leg_dist_mi": 0.17468172661158093,
      "cum_dist_mi": 32.32007355784313
    },
    {
      "start_lat_lon": {
        "lat": 47.77674,
        "lon": -121.06762
      },
      "leg_dist_mi": 0.24205168924386314,
      "cum_dist_mi": 32.49475528445471
    },
    {
      "start_lat_lon": {
        "lat": 47.77431,
        "lon": -121.07138
      },
      "leg_dist_mi": 0.1912259705994215,
      "cum_dist_mi": 32.73680697369858
    },
    {
      "start_lat_lon": {
        "lat": 47.77239,
        "lon": -121.07435
      },
      "leg_dist_mi": 0.18728671233121225,
      "cum_dist_mi": 32.928032944297996
    },
    {
      "start_lat_lon": {
        "lat": 47.77025,
        "lon": -121.07683
      },
      "leg_dist_mi": 0.06765691812787492,
      "cum_dist_mi": 33.11531965662921
    },
    {
      "start_lat_lon": {
        "lat": 47.76936,
        "lon": -121.07744
      },
      "leg_dist_mi": 0.04691116744599754,
      "cum_dist_mi": 33.182976574757085
    },
    {
      "start_lat_lon": {
        "lat": 47.7687,
        "lon": -121.07768
      },
      "leg_dist_mi": 0.05260554107887933,
      "cum_dist_mi": 33.22988774220308
    },
    {
      "start_lat_lon": {
        "lat": 47.76794,
        "lon": -121.07776
      },
      "leg_dist_mi": 0.053863273201749155,
      "cum_dist_mi": 33.282493283281966
    },
    {
      "start_lat_lon": {
        "lat": 47.76716,
        "lon": -121.07774
      },
      "leg_dist_mi": 0.09760233874018655,
      "cum_dist_mi": 33.336356556483715
    },
    {
      "start_lat_lon": {
        "lat": 47.76575,
        "lon": -121.07759
      },
      "leg_dist_mi": 0.07493354435753093,
      "cum_dist_mi": 33.4339588952239
    },
    {
      "start_lat_lon": {
        "lat": 47.76468,
        "lon": -121.07732
      },
      "leg_dist_mi": 0.058762452566871626,
      "cum_dist_mi": 33.50889243958143
    },
    {
      "start_lat_lon": {
        "lat": 47.76385,
        "lon": -121.07704
      },
      "leg_dist_mi": 0.19899997851777845,
      "cum_dist_mi": 33.567654892148305
    },
    {
      "start_lat_lon": {
        "lat": 47.76111,
        "lon": -121.07571
      },
      "leg_dist_mi": 0.09282947161743693,
      "cum_dist_mi": 33.76665487066608
    },
    {
      "start_lat_lon": {
        "lat": 47.7598,
        "lon": -121.07526
      },
      "leg_dist_mi": 0.08079491364683936,
      "cum_dist_mi": 33.859484342283515
    },
    {
      "start_lat_lon": {
        "lat": 47.75863,
        "lon": -121.07529
      },
      "leg_dist_mi": 0.08702250570992484,
      "cum_dist_mi": 33.940279255930356
    },
    {
      "start_lat_lon": {
        "lat": 47.75738,
        "lon": -121.07553
      },
      "leg_dist_mi": 0.09516555542001302,
      "cum_dist_mi": 34.02730176164028
    },
    {
      "start_lat_lon": {
        "lat": 47.75604,
        "lon": -121.07601
      },
      "leg_dist_mi": 0.12354159445394904,
      "cum_dist_mi": 34.12246731706029
    },
    {
      "start_lat_lon": {
        "lat": 47.75442,
        "lon": -121.07714
      },
      "leg_dist_mi": 0.19077373312464532,
      "cum_dist_mi": 34.24600891151424
    },
    {
      "start_lat_lon": {
        "lat": 47.75201,
        "lon": -121.07915
      },
      "leg_dist_mi": 0.0673471197515494,
      "cum_dist_mi": 34.43678264463888
    },
    {
      "start_lat_lon": {
        "lat": 47.75121,
        "lon": -121.07998
      },
      "leg_dist_mi": 0.21998003851485617,
      "cum_dist_mi": 34.504129764390434
    },
    {
      "start_lat_lon": {
        "lat": 47.74895,
        "lon": -121.08332
      },
      "leg_dist_mi": 0.1125871964956759,
      "cum_dist_mi": 34.72410980290529
    },
    {
      "start_lat_lon": {
        "lat": 47.74788,
        "lon": -121.08515
      },
      "leg_dist_mi": 0.07939431622731154,
      "cum_dist_mi": 34.836696999400964
    },
    {
      "start_lat_lon": {
        "lat": 47.74738,
        "lon": -121.08669
      },
      "leg_dist_mi": 0.06721138133453194,
      "cum_dist_mi": 34.91609131562827
    },
    {
      "start_lat_lon": {
        "lat": 47.74678,
        "lon": -121.08783
      },
      "leg_dist_mi": 0.023904693785738455,
      "cum_dist_mi": 34.9833026969628
    },
    {
      "start_lat_lon": {
        "lat": 47.74652,
        "lon": -121.08817
      },
      "leg_dist_mi": 0.03214443014670048,
      "cum_dist_mi": 35.00720739074854
    },
    {
      "start_lat_lon": {
        "lat": 47.74614,
        "lon": -121.08857
      },
      "leg_dist_mi": 0.017356752055644513,
      "cum_dist_mi": 35.03935182089524
    },
    {
      "start_lat_lon": {
        "lat": 47.74599,
        "lon": -121.08827
      },
      "leg_dist_mi": 0.01901584433193825,
      "cum_dist_mi": 35.05670857295089
    },
    {
      "start_lat_lon": {
        "lat": 47.74581,
        "lon": -121.08796
      },
      "leg_dist_mi": 0.003922680952276697,
      "cum_dist_mi": 35.07572441728283
    },
    {
      "start_lat_lon": {
        "lat": 47.74577,
        "lon": -121.0879
      },
      "leg_dist_mi": 0.011167930289528583,
      "cum_dist_mi": 35.07964709823511
    },
    {
      "start_lat_lon": {
        "lat": 47.74562,
        "lon": -121.08781
      },
      "leg_dist_mi": 0.048832406569056096,
      "cum_dist_mi": 35.09081502852464
    },
    {
      "start_lat_lon": {
        "lat": 47.74503,
        "lon": -121.08839
      },
      "leg_dist_mi": 0.011883697010744118,
      "cum_dist_mi": 35.13964743509369
    },
    {
      "start_lat_lon": {
        "lat": 47.74486,
        "lon": -121.08843
      },
      "leg_dist_mi": 0.006075043709095156,
      "cum_dist_mi": 35.15153113210444
    },
    {
      "start_lat_lon": {
        "lat": 47.74485,
        "lon": -121.0883
      },
      "leg_dist_mi": 0.04461292188936093,
      "cum_dist_mi": 35.157606175813534
    },
    {
      "start_lat_lon": {
        "lat": 47.74536,
        "lon": -121.08771
      },
      "leg_dist_mi": 0.06051086871079686,
      "cum_dist_mi": 35.202219097702894
    },
    {
      "start_lat_lon": {
        "lat": 47.74596,
        "lon": -121.08676
      },
      "leg_dist_mi": 0.012328756827506204,
      "cum_dist_mi": 35.262729966413694
    },
    {
      "start_lat_lon": {
        "lat": 47.74606,
        "lon": -121.08654
      },
      "leg_dist_mi": 0.0,
      "cum_dist_mi": 35.2750587232412
    }
  ]
}