{
  "start_city": "Los Angeles",
  "start_state": "CA",
  "start_lat_lon": {
    "lat": 34.0549067,
    "lon": -118.2426508
  },
  "end_city": "San Diego",
  "end_state": "CA",
  "end_lat_lon": {
    "lat": 32.7157323,
    "lon": -117.1610969
  },
  "total_length_mi": 121.0,
  "legs": [
    {
      "start_lat_lon": {
        "lat": 34.05491,
        "lon": -118.24265
      },
      "leg_dist_mi": 0.2724845230551766,
      "cum_dist_mi": 0.0
    },
    {
      "start_lat_lon": {
        "lat": 34.05774,
        "lon": -118.24597
      },
      "leg_dist_mi": 0.11877961867169044,
      "cum_dist_mi": 0.2724845230551766
    },
    {
      "start_lat_lon": {
        "lat": 34.05904,
        "lon": -118.24733
      },
      "leg_dist_mi": 0.041334463510119025,
      "cum_dist_mi": 0.3912641417268671
    },
    {
      "start_lat_lon": {
        "lat": 34.05948,
        "lon": -118.24684
      },
      "leg_dist_mi": 0.05035958348284771,
      "cum_dist_mi": 0.4325986052369861
    },
    {
      "start_lat_lon": {
        "lat": 34.05929,
        "lon": -118.24599
      },
      "leg_dist_mi": 0.20967548143255235,
      "cum_dist_mi": 0.4829581887198338
    },
    {
      "start_lat_lon": {
        "lat": 34.05734,
        "lon": -118.24318
      },
      "leg_dist_mi": 0.38921623609879497,
      "cum_dist_mi": 0.6926336701523862
    },
    {
      "start_lat_lon": {
        "lat": 34.05401,
        "lon": -118.23769
      },
      "leg_dist_mi": 0.4074825153722851,
      "cum_dist_mi": 1.0818499062511813
    },
    {
      "start_lat_lon": {
        "lat": 34.05329,
        "lon": -118.23062
      },
      "leg_dist_mi": 0.3329168302734883,
      "cum_dist_mi": 1.4893324216234665
    },
    {
      "start_lat_lon": {
        "lat": 34.05224,
        "lon": -118.22494
      },
      "leg_dist_mi": 0.10617919848894611,
      "cum_dist_mi": 1.8222492518969546
    },
    {
      "start_lat_lon": {
        "lat": 34.05128,
        "lon": -118.22349
      },
      "leg_dist_mi": 0.2158346143524924,
      "cum_dist_mi": 1.9284284503859008
    },
    {
      "start_lat_lon": {
        "lat": 34.04843,
        "lon": -118.22194
      },
      "leg_dist_mi": 0.3631680662888143,
      "cum_dist_mi": 2.1442630647383933
    },
    {
      "start_lat_lon": {
        "lat": 34.04321,
        "lon": -118.22116
      },
      "leg_dist_mi": 0.3910312242316068,
      "cum_dist_mi": 2.5074311310272077
    },
    {
      "start_lat_lon": {
        "lat": 34.03756,
        "lon": -118.22163
      },
      "leg_dist_mi": 0.1410798495268389,
      "cum_dist_mi": 2.8984623552588147
    },
    {
      "start_lat_lon": {
        "lat": 34.03552,
        "lon": -118.22177
      },
      "leg_dist_mi": 0.165105456312739,
      "cum_dist_mi": 3.0395422047856537
    },
    {
      "start_lat_lon": {
        "lat": 34.03328,
        "lon": -118.22076
      },
      "leg_dist_mi": 0.3106496169463221,
      "cum_dist_mi": 3.204647661098393
    },
    {
      "start_lat_lon": {
        "lat": 34.03015,
        "lon": -118.21686
      },
      "leg_dist_mi": 0.8608667532442749,
      "cum_dist_mi": 3.515297278044715
    },
    {
      "start_lat_lon": {
        "lat": 34.02445,
        "lon": -118.20348
      },
      "leg_dist_mi": 0.4450616528494914,
      "cum_dist_mi": 4.37616403128899
    },
    {
      "start_lat_lon": {
        "lat": 34.02146,
        "lon": -118.19659
      },
      "leg_dist_mi": 0.2427440870060242,
      "cum_dist_mi": 4.821225684138482
    },
    {
      "start_lat_lon": {
        "lat": 34.0202,
        "lon": -118.19263
      },
      "leg_dist_mi": 0.3634891350161058,
      "cum_dist_mi": 5.063969771144506
    },
    {
      "start_lat_lon": {
        "lat": 34.02008,
        "lon": -118.18628
      },
      "leg_dist_mi": 0.3044931456058235,
      "cum_dist_mi": 5.427458906160611
    },
    {
      "start_lat_lon": {
        "lat": 34.0198,
        "lon": -118.18097
      },
      "leg_dist_mi": 0.44433286503498554,
      "cum_dist_mi": 5.731952051766434
    },
    {
      "start_lat_lon": {
        "lat": 34.01662,
        "lon": -118.17422
      },
      "leg_dist_mi": 0.3429574665021526,
      "cum_dist_mi": 6.1762849168014196
    },
    {
      "start_lat_lon": {
        "lat": 34.01461,
        "lon": -118.16874
      },
      "leg_dist_mi": 0.3805827419511504,
      "cum_dist_mi": 6.519242383303572
    },
    {
      "start_lat_lon": {
        "lat": 34.01202,
        "lon": -118.16287
      },
      "leg_dist_mi": 0.16803630189071153,
      "cum_dist_mi": 6.899825125254723
    },
    {
      "start_lat_lon": {
        "lat": 34.01063,
        "lon": -118.16046
      },
      "leg_dist_mi": 0.13975853453029619,
      "cum_dist_mi": 7.067861427145434
    },
    {
      "start_lat_lon": {
        "lat": 34.00902,
        "lon": -118.15898
      },
      "leg_dist_mi": 0.2677160913015305,
      "cum_dist_mi": 7.20761996167573
    },
    {
      "start_lat_lon": {
        "lat": 34.00642,
        "lon": -118.15551
      },
      "leg_dist_mi": 0.6829161574642548,
      "cum_dist_mi": 7.475336052977261
    },
    {
      "start_lat_lon": {
        "lat": 33.9989,
        "lon": -118.14776
      },
      "leg_dist_mi": 0.29652148902363284,
      "cum_dist_mi": 8.158252210441516
    },
    {
      "start_lat_lon": {
        "lat": 33.99524,
        "lon": -118.14505
      },
      "leg_dist_mi": 0.6170047825918892,
      "cum_dist_mi": 8.454773699465148
    },
    {
      "start_lat_lon": {
        "lat": 33.98826,
        "lon": -118.13832
      },
      "leg_dist_mi": 0.33214073919528647,
      "cum_dist_mi": 9.071778482057038
    },
    {
      "start_lat_lon": {
        "lat": 33.98489,
        "lon": -118.13418
      },
      "leg_dist_mi": 0.38726427431891075,
      "cum_dist_mi": 9.403919221252325
    },
    {
      "start_lat_lon": {
        "lat": 33.98063,
        "lon": -118.12978
      },
      "leg_dist_mi": 0.36908776307955193,
      "cum_dist_mi": 9.791183495571236
    },
    {
      "start_lat_lon": {
        "lat": 33.97638,
        "lon": -118.12587
      },
      "leg_dist_mi": 0.28281277429786755,
      "cum_dist_mi": 10.160271258650788
    },
    {
      "start_lat_lon": {
        "lat": 33.9728,
        "lon": -118.12347
      },
      "leg_dist_mi": 0.27929411014155653,
      "cum_dist_mi": 10.443084032948656
    },
    {
      "start_lat_lon": {
        "lat": 33.96889,
        "lon": -118.12222
      },
      "leg_dist_mi": 0.25352300093783803,
      "cum_dist_mi": 10.722378143090213
    },
    {
      "start_lat_lon": {
        "lat": 33.96537,
        "lon": -118.12096
      },
      "leg_dist_mi": 0.11914950865574456,
      "cum_dist_mi": 10.97590114402805
    },
    {
      "start_lat_lon": {
        "lat": 33.96389,
        "lon": -118.11989
      },
      "leg_dist_mi": 0.2854744258418105,
      "cum_dist_mi": 11.095050652683796
    },
    {
      "start_lat_lon": {
        "lat": 33.96103,
        "lon": -118.11629
      },
      "leg_dist_mi": 0.31832755906161014,
      "cum_dist_mi": 11.380525078525606
    },
    {
      "start_lat_lon": {
        "lat": 33.95801,
        "lon": -118.11209
      },
      "leg_dist_mi": 0.36549734041444887,
      "cum_dist_mi": 11.698852637587215
    },
    {
      "start_lat_lon": {
        "lat": 33.95455,
        "lon": -118.10726
      },
      "leg_dist_mi": 0.2345417097941698,
      "cum_dist_mi": 12.064349978001664
    },
    {
      "start_lat_lon": {
        "lat": 33.95222,
        "lon": -118.10428
      },
      "leg_dist_mi": 0.16416425407708193,
      "cum_dist_mi": 12.298891687795834
    },
    {
      "start_lat_lon": {
        "lat": 33.95022,
        "lon": -118.10273
      },
      "leg_dist_mi": 0.4402646791285691,
      "cum_dist_mi": 12.463055941872916
    },
    {
      "start_lat_lon": {
        "lat": 33.94464,
        "lon": -118.09901
      },
      "leg_dist_mi": 0.4030027062406925,
      "cum_dist_mi": 12.903320621001486
    },
    {
      "start_lat_lon": {
        "lat": 33.93953,
        "lon": -118.09561
      },
      "leg_dist_mi": 1.0303897666798372,
      "cum_dist_mi": 13.306323327242179
    },
    {
      "start_lat_lon": {
        "lat": 33.92651,
        "lon": -118.08682
      },
      "leg_dist_mi": 0.880004380698844,
      "cum_dist_mi": 14.336713093922016
    },
    {
      "start_lat_lon": {
        "lat": 33.91563,
        "lon": -118.07882
      },
      "leg_dist_mi": 0.408322234859762,
      "cum_dist_mi": 15.21671747462086
    },
    {
      "start_lat_lon": {
        "lat": 33.91181,
        "lon": -118.07338
      },
      "leg_dist_mi": 0.3753864969990832,
      "cum_dist_mi": 15.625039709480623
    },
    {
      "start_lat_lon": {
        "lat": 33.90811,
        "lon": -118.06858
      },
      "leg_dist_mi": 0.43249291507459503,
      "cum_dist_mi": 16.000426206479705
    },
    {
      "start_lat_lon": {
        "lat": 33.90336,
        "lon": -118.06366
      },
      "leg_dist_mi": 0.3729192720283182,
      "cum_dist_mi": 16.4329191215543
    },
    {
      "start_lat_lon": {
        "lat": 33.90008,
        "lon": -118.05849
      },
      "leg_dist_mi": 1.1067187846247055,
      "cum_dist_mi": 16.80583839358262
    },
    {
      "start_lat_lon": {
        "lat": 33.89113,
        "lon": -118.04247
      },
      "leg_dist_mi": 0.6292530554313668,
      "cum_dist_mi": 17.912557178207322
    },
    {
      "start_lat_lon": {
        "lat": 33.88634,
        "lon": -118.03313
      },
      "leg_dist_mi": 0.7479401887429514,
      "cum_dist_mi": 18.54181023363869
    },
    {
      "start_lat_lon": {
        "lat": 33.88014,
        "lon": -118.02243
      },
      "leg_dist_mi": 0.43265536139733435,
      "cum_dist_mi": 19.28975042238164
    },
    {
      "start_lat_lon": {
        "lat": 33.8771,
        "lon": -118.01583
      },
      "leg_dist_mi": 0.4918017147920533,
      "cum_dist_mi": 19.722405783778974
    },
    {
      "start_lat_lon": {
        "lat": 33.87261,
        "lon": -118.00917
      },
      "leg_dist_mi": 0.34160885677902814,
      "cum_dist_mi": 20.214207498571028
    },
    {
      "start_lat_lon": {
        "lat": 33.86959,
        "lon": -118.00445
      },
      "leg_dist_mi": 0.8019332291373681,
      "cum_dist_mi": 20.555816355350057
    },
    {
      "start_lat_lon": {
        "lat": 33.86325,
        "lon": -117.99273
      },
      "leg_dist_mi": 0.316406187151491,
      "cum_dist_mi": 21.357749584487426
    },
    {
      "start_lat_lon": {
        "lat": 33.86043,
        "lon": -117.98838
      },
      "leg_dist_mi": 0.5047209883723209,
      "cum_dist_mi": 21.674155771638915
    },
    {
      "start_lat_lon": {
        "lat": 33.85677,
        "lon": -117.98076
      },
      "leg_dist_mi": 0.19681060786467347,
      "cum_dist_mi": 22.178876760011235
    },
    {
      "start_lat_lon": {
        "lat": 33.8556,
        "lon": -117.97763
      },
      "leg_dist_mi": 0.19200379445715982,
      "cum_dist_mi": 22.37568736787591
    },
    {
      "start_lat_lon": {
        "lat": 33.8539,
        "lon": -117.97498
      },
      "leg_dist_mi": 0.3895344754291574,
      "cum_dist_mi": 22.56769116233307
    },
    {
      "start_lat_lon": {
        "lat": 33.8506,
        "lon": -117.96947
      },
      "leg_dist_mi": 0.5594254854439425,
      "cum_dist_mi": 22.957225637762228
    },
    {
      "start_lat_lon": {
        "lat": 33.84641,
        "lon": -117.96112
      },
      "leg_dist_mi": 1.0485474978269689,
      "cum_dist_mi": 23.51665112320617
    },
    {
      "start_lat_lon": {
        "lat": 33.83792,
        "lon": -117.94596
      },
      "leg_dist_mi": 0.2633967606870088,
      "cum_dist_mi": 24.56519862103314
    },
    {
      "start_lat_lon": {
        "lat": 33.83584,
        "lon": -117.94211
      },
      "leg_dist_mi": 0.38392736518481657,
      "cum_dist_mi": 24.82859538172015
    },
    {
      "start_lat_lon": {
        "lat": 33.83396,
        "lon": -117.93581
      },
      "leg_dist_mi": 0.29109835464437617,
      "cum_dist_mi": 25.212522746904966
    },
    {
      "start_lat_lon": {
        "lat": 33.83163,
        "lon": -117.93158
      },
      "leg_dist_mi": 0.45509487898121936,
      "cum_dist_mi": 25.503621101549342
    },
    {
      "start_lat_lon": {
        "lat": 33.82663,
        "lon": -117.92641
      },
      "leg_dist_mi": 0.473683174570202,
      "cum_dist_mi": 25.958715980530563
    },
    {
      "start_lat_lon": {
        "lat": 33.82112,
        "lon": -117.92149
      },
      "leg_dist_mi": 0.5677596556291524,
      "cum_dist_mi": 26.432399155100764
    },
    {
      "start_lat_lon": {
        "lat": 33.81489,
        "lon": -117.91503
      },
      "leg_dist_mi": 0.8097487767989794,
      "cum_dist_mi": 27.000158810729918
    },
    {
      "start_lat_lon": {
        "lat": 33.80601,
        "lon": -117.90581
      },
      "leg_dist_mi": 0.9037898850491175,
      "cum_dist_mi": 27.809907587528897
    },
    {
      "start_lat_lon": {
        "lat": 33.79623,
        "lon": -117.89534
      },
      "leg_dist_mi": 0.8630400607568078,
      "cum_dist_mi": 28.713697472578016
    },
    {
      "start_lat_lon": {
        "lat": 33.78682,
        "lon": -117.88544
      },
      "leg_dist_mi": 0.37595188656599887,
      "cum_dist_mi": 29.576737533334825
    },
    {
      "start_lat_lon": {
        "lat": 33.7826,
        "lon": -117.8813
      },
      "leg_dist_mi": 0.4232279713536861,
      "cum_dist_mi": 29.952689419900825
    },
    {
      "start_lat_lon": {
        "lat": 33.77827,
        "lon": -117.87608
      },
      "leg_dist_mi": 0.5473678547035051,
      "cum_dist_mi": 30.37591739125451
    },
    {
      "start_lat_lon": {
        "lat": 33.77177,
        "lon": -117.87062
      },
      "leg_dist_mi": 0.46584153405533313,
      "cum_dist_mi": 30.923285245958017
    },
    {
      "start_lat_lon": {
        "lat": 33.76589,
        "lon": -117.86664
      },
      "leg_dist_mi": 0.41554129946641527,
      "cum_dist_mi": 31.38912678001335
    },
    {
      "start_lat_lon": {
        "lat": 33.76059,
        "lon": -117.86321
      },
      "leg_dist_mi": 0.16681279598759233,
      "cum_dist_mi": 31.804668079479764
    },
    {
      "start_lat_lon": {
        "lat": 33.75892,
        "lon": -117.86111
      },
      "leg_dist_mi": 0.34114280625857285,
      "cum_dist_mi": 31.971480875467357
    },
    {
      "start_lat_lon": {
        "lat": 33.75644,
        "lon": -117.85597
      },
      "leg_dist_mi": 0.5754866839395356,
      "cum_dist_mi": 32.31262368172593
    },
    {
      "start_lat_lon": {
        "lat": 33.75227,
        "lon": -117.84729
      },
      "leg_dist_mi": 0.29779406633496136,
      "cum_dist_mi": 32.88811036566547
    },
    {
      "start_lat_lon": {
        "lat": 33.74897,
        "lon": -117.84395
      },
      "leg_dist_mi": 0.24881312001015315,
      "cum_dist_mi": 33.18590443200043
    },
    {
      "start_lat_lon": {
        "lat": 33.74558,
        "lon": -117.84248
      },
      "leg_dist_mi": 0.19737605688172788,
      "cum_dist_mi": 33.43471755201058
    },
    {
      "start_lat_lon": {
        "lat": 33.74322,
        "lon": -117.84054
      },
      "leg_dist_mi": 0.18261796492969637,
      "cum_dist_mi": 33.63209360889231
    },
    {
      "start_lat_lon": {
        "lat": 33.74192,
        "lon": -117.83777
      },
      "leg_dist_mi": 0.2531525816647794,
      "cum_dist_mi": 33.81471157382201
    },
    {
      "start_lat_lon": {
        "lat": 33.74049,
        "lon": -117.83371
      },
      "leg_dist_mi": 0.9108757174682781,
      "cum_dist_mi": 34.06786415548679
    },
    {
      "start_lat_lon": {
        "lat": 33.73555,
        "lon": -117.819
      },
      "leg_dist_mi": 1.6848720615088209,
      "cum_dist_mi": 34.97873987295507
    },
    {
      "start_lat_lon": {
        "lat": 33.72016,
        "lon": -117.79623
      },
      "leg_dist_mi": 0.6159386924755399,
      "cum_dist_mi": 36.66361193446389
    },
    {
      "start_lat_lon": {
        "lat": 33.71444,
        "lon": -117.788
      },
      "leg_dist_mi": 0.5794776890527327,
      "cum_dist_mi": 37.279550626939425
    },
    {
      "start_lat_lon": {
        "lat": 33.70842,
        "lon": -117.78097
      },
      "leg_dist_mi": 1.9043915879121303,
      "cum_dist_mi": 37.859028315992155
    },
    {
      "start_lat_lon": {
        "lat": 33.6843,
        "lon": -117.76489
      },
      "leg_dist_mi": 0.7416779239824962,
      "cum_dist_mi": 39.763419903904285
    },
    {
      "start_lat_lon": {
        "lat": 33.67585,
        "lon": -117.75692
      },
      "leg_dist_mi": 0.301571377005925,
      "cum_dist_mi": 40.50509782788678
    },
    {
      "start_lat_lon": {
        "lat": 33.67161,
        "lon": -117.75566
      },
      "leg_dist_mi": 0.16631537787702078,
      "cum_dist_mi": 40.80666920489271
    },
    {
      "start_lat_lon": {
        "lat": 33.66931,
        "lon": -117.7548
      },
      "leg_dist_mi": 0.17371202486861262,
      "cum_dist_mi": 40.972984582769726
    },
    {
      "start_lat_lon": {
        "lat": 33.66716,
        "lon": -117.75323
      },
      "leg_dist_mi": 0.5348589064073729,
      "cum_dist_mi": 41.14669660763834
    },
    {
      "start_lat_lon": {
        "lat": 33.66068,
        "lon": -117.74813
      },
      "leg_dist_mi": 0.5346017884210291,
      "cum_dist_mi": 41.68155551404571
    },
    {
      "start_lat_lon": {
        "lat": 33.65426,
        "lon": -117.74293
      },
      "leg_dist_mi": 0.8244459748372304,
      "cum_dist_mi": 42.21615730246674
    },
    {
      "start_lat_lon": {
        "lat": 33.64431,
        "lon": -117.735
      },
      "leg_dist_mi": 0.567896754681734,
      "cum_dist_mi": 43.04060327730397
    },
    {
      "start_lat_lon": {
        "lat": 33.63739,
        "lon": -117.72966
      },
      "leg_dist_mi": 0.34465821968804133,
      "cum_dist_mi": 43.608500031985706
    },
    {
      "start_lat_lon": {
        "lat": 33.63329,
        "lon": -117.72624
      },
      "leg_dist_mi": 0.29932710329155315,
      "cum_dist_mi": 43.95315825167375
    },
    {
      "start_lat_lon": {
        "lat": 33.63015,
        "lon": -117.72265
      },
      "leg_dist_mi": 0.781040526454315,
      "cum_dist_mi": 44.2524853549653
    },
    {
      "start_lat_lon": {
        "lat": 33.62124,
        "lon": -117.71428
      },
      "leg_dist_mi": 0.5359507645254172,
      "cum_dist_mi": 45.033525881419614
    },
    {
      "start_lat_lon": {
        "lat": 33.61519,
        "lon": -117.70844
      },
      "leg_dist_mi": 0.33343938814691654,
      "cum_dist_mi": 45.56947664594503
    },
    {
      "start_lat_lon": {
        "lat": 33.61175,
        "lon": -117.70437
      },
      "leg_dist_mi": 0.38297362657943546,
      "cum_dist_mi": 45.902916034091945
    },
    {
      "start_lat_lon": {
        "lat": 33.60855,
        "lon": -117.69893
      },
      "leg_dist_mi": 0.328501713750553,
      "cum_dist_mi": 46.28588966067138
    },
    {
      "start_lat_lon": {
        "lat": 33.60639,
        "lon": -117.69384
      },
      "leg_dist_mi": 0.4972548434259037,
      "cum_dist_mi": 46.614391374421935
    },
    {
      "start_lat_lon": {
        "lat": 33.60222,
        "lon": -117.68679
      },
      "leg_dist_mi": 0.3456893894436144,
      "cum_dist_mi": 47.11164621784784
    },
    {
      "start_lat_lon": {
        "lat": 33.60009,
        "lon": -117.68135
      },
      "leg_dist_mi": 0.30588614739962416,
      "cum_dist_mi": 47.457335607291455
    },
    {
      "start_lat_lon": {
        "lat": 33.59813,
        "lon": -117.67658
      },
      "leg_dist_mi": 0.1373450790124611,
      "cum_dist_mi": 47.76322175469108
    },
    {
      "start_lat_lon": {
        "lat": 33.59675,
        "lon": -117.67486
      },
      "leg_dist_mi": 0.23898658072781398,
      "cum_dist_mi": 47.90056683370354
    },
    {
      "start_lat_lon": {
        "lat": 33.59384,
        "lon": -117.67261
      },
      "leg_dist_mi": 0.13016225444327656,
      "cum_dist_mi": 48.139553414431354
    },
    {
      "start_lat_lon": {
        "lat": 33.59205,
        "lon": -117.6719
      },
      "leg_dist_mi": 0.5240734597195164,
      "cum_dist_mi": 48.26971566887463
    },
    {
      "start_lat_lon": {
        "lat": 33.58446,
        "lon": -117.67182
      },
      "leg_dist_mi": 0.5144332396600516,
      "cum_dist_mi": 48.79378912859415
    },
    {
      "start_lat_lon": {
        "lat": 33.57701,
        "lon": -117.67194
      },
      "leg_dist_mi": 0.6554977338141228,
      "cum_dist_mi": 49.3082223682542
    },
    {
      "start_lat_lon": {
        "lat": 33.56752,
        "lon": -117.67226
      },
      "leg_dist_mi": 0.7481333184818877,
      "cum_dist_mi": 49.96372010206832
    },
    {
      "start_lat_lon": {
        "lat": 33.55671,
        "lon": -117.67315
      },
      "leg_dist_mi": 0.5677197379239196,
      "cum_dist_mi": 50.71185342055021
    },
    {
      "start_lat_lon": {
        "lat": 33.54849,
        "lon": -117.67291
      },
      "leg_dist_mi": 0.3533809148904184,
      "cum_dist_mi": 51.279573158474136
    },
    {
      "start_lat_lon": {
        "lat": 33.54342,
        "lon": -117.67375
      },
      "leg_dist_mi": 0.446330137858637,
      "cum_dist_mi": 51.63295407336455
    },
    {
      "start_lat_lon": {
        "lat": 33.53705,
        "lon": -117.67507
      },
      "leg_dist_mi": 0.2844756428243425,
      "cum_dist_mi": 52.07928421122319
    },
    {
      "start_lat_lon": {
        "lat": 33.53293,
        "lon": -117.67503
      },
      "leg_dist_mi": 0.1429470524299103,
      "cum_dist_mi": 52.36375985404753
    },
    {
      "start_lat_lon": {
        "lat": 33.53097,
        "lon": -117.67423
      },
      "leg_dist_mi": 0.27460148773461274,
      "cum_dist_mi": 52.50670690647744
    },
    {
      "start_lat_lon": {
        "lat": 33.52813,
        "lon": -117.67089
      },
      "leg_dist_mi": 0.20547072964403354,
      "cum_dist_mi": 52.781308394212054
    },
    {
      "start_lat_lon": {
        "lat": 33.52595,
        "lon": -117.66846
      },
      "leg_dist_mi": 0.1954417522947281,
      "cum_dist_mi": 52.98677912385609
    },
    {
      "start_lat_lon": {
        "lat": 33.52336,
        "lon": -117.66709
      },
      "leg_dist_mi": 0.5570947659469743,
      "cum_dist_mi": 53.182220876150815
    },
    {
      "start_lat_lon": {
        "lat": 33.51576,
        "lon": -117.66384
      },
      "leg_dist_mi": 0.6728098766174663,
      "cum_dist_mi": 53.739315642097786
    },
    {
      "start_lat_lon": {
        "lat": 33.50658,
        "lon": -117.65992
      },
      "leg_dist_mi": 0.2311488662933603,
      "cum_dist_mi": 54.41212551871525
    },
    {
      "start_lat_lon": {
        "lat": 33.50337,
        "lon": -117.65878
      },
      "leg_dist_mi": 0.22769007108391076,
      "cum_dist_mi": 54.64327438500861
    },
    {
      "start_lat_lon": {
        "lat": 33.50008,
        "lon": -117.65851
      },
      "leg_dist_mi": 0.2776637355041508,
      "cum_dist_mi": 54.87096445609252
    },
    {
      "start_lat_lon": {
        "lat": 33.49612,
        "lon": -117.65935
      },
      "leg_dist_mi": 0.2559063693735516,
      "cum_dist_mi": 55.14862819159667
    },
    {
      "start_lat_lon": {
        "lat": 33.49275,
        "lon": -117.6612
      },
      "leg_dist_mi": 0.46346572138165865,
      "cum_dist_mi": 55.40453456097022
    },
    {
      "start_lat_lon": {
        "lat": 33.48706,
        "lon": -117.66547
      },
      "leg_dist_mi": 0.7350716446292445,
      "cum_dist_mi": 55.86800028235188
    },
    {
      "start_lat_lon": {
        "lat": 33.47835,
        "lon": -117.67281
      },
      "leg_dist_mi": 0.2830389012608731,
      "cum_dist_mi": 56.60307192698112
    },
    {
      "start_lat_lon": {
        "lat": 33.47458,
        "lon": -117.67474
      },
      "leg_dist_mi": 0.18787453114115363,
      "cum_dist_mi": 56.886110828241996
    },
    {
      "start_lat_lon": {
        "lat": 33.47186,
        "lon": -117.67483
      },
      "leg_dist_mi": 0.19598341037013148,
      "cum_dist_mi": 57.07398535938315
    },
    {
      "start_lat_lon": {
        "lat": 33.46923,
        "lon": -117.67355
      },
      "leg_dist_mi": 0.17183216620430483,
      "cum_dist_mi": 57.269968769753284
    },
    {
      "start_lat_lon": {
        "lat": 33.46754,
        "lon": -117.67136
      },
      "leg_dist_mi": 0.19161886090766206,
      "cum_dist_mi": 57.44180093595759
    },
    {
      "start_lat_lon": {
        "lat": 33.46618,
        "lon": -117.66846
      },
      "leg_dist_mi": 0.4002902736604147,
      "cum_dist_mi": 57.63341979686525
    },
    {
      "start_lat_lon": {
        "lat": 33.4625,
        "lon": -117.66309
      },
      "leg_dist_mi": 0.32139351688537443,
      "cum_dist_mi": 58.033710070525665
    },
    {
      "start_lat_lon": {
        "lat": 33.45994,
        "lon": -117.65843
      },
      "leg_dist_mi": 0.7573413785796822,
      "cum_dist_mi": 58.35510358741104
    },
    {
      "start_lat_lon": {
        "lat": 33.45425,
        "lon": -117.64719
      },
      "leg_dist_mi": 0.33664623354916584,
      "cum_dist_mi": 59.11244496599072
    },
    {
      "start_lat_lon": {
        "lat": 33.45174,
        "lon": -117.64218
      },
      "leg_dist_mi": 0.35829554787615975,
      "cum_dist_mi": 59.449091199539886
    },
    {
      "start_lat_lon": {
        "lat": 33.44842,
        "lon": -117.6374
      },
      "leg_dist_mi": 0.395849929181698,
      "cum_dist_mi": 59.80738674741605
    },
    {
      "start_lat_lon": {
        "lat": 33.44532,
        "lon": -117.63162
      },
      "leg_dist_mi": 0.41887724034501045,
      "cum_dist_mi": 60.20323667659775
    },
    {
      "start_lat_lon": {
        "lat": 33.44108,
        "lon": -117.62642
      },
      "leg_dist_mi": 0.5213969005881464,
      "cum_dist_mi": 60.62211391694276
    },
    {
      "start_lat_lon": {
        "lat": 33.43664,
        "lon": -117.6191
      },
      "leg_dist_mi": 0.5337056220652634,
      "cum_dist_mi": 61.1435108175309
    },
    {
      "start_lat_lon": {
        "lat": 33.43033,
        "lon": -117.61375
      },
      "leg_dist_mi": 0.29619705770342336,
      "cum_dist_mi": 61.677216439596165
    },
    {
      "start_lat_lon": {
        "lat": 33.42694,
        "lon": -117.6106
      },
      "leg_dist_mi": 0.2534586540820177,
      "cum_dist_mi": 61.97341349729959
    },
    {
      "start_lat_lon": {
        "lat": 33.42371,
        "lon": -117.60851
      },
      "leg_dist_mi": 0.4997546520122123,
      "cum_dist_mi": 62.226872151381606
    },
    {
      "start_lat_lon": {
        "lat": 33.41735,
        "lon": -117.60437
      },
      "leg_dist_mi": 1.0337599347071218,
      "cum_dist_mi": 62.72662680339382
    },
    {
      "start_lat_lon": {
        "lat": 33.40353,
        "lon": -117.59747
      },
      "leg_dist_mi": 0.7162074169154721,
      "cum_dist_mi": 63.76038673810094
    },
    {
      "start_lat_lon": {
        "lat": 33.39409,
        "lon": -117.59232
      },
      "leg_dist_mi": 0.5166501957172542,
      "cum_dist_mi": 64.47659415501641
    },
    {
      "start_lat_lon": {
        "lat": 33.38788,
        "lon": -117.58732
      },
      "leg_dist_mi": 0.2645008627960382,
      "cum_dist_mi": 64.99324435073368
    },
    {
      "start_lat_lon": {
        "lat": 33.38557,
        "lon": -117.58366
      },
      "leg_dist_mi": 0.32112235903681663,
      "cum_dist_mi": 65.25774521352972
    },
    {
      "start_lat_lon": {
        "lat": 33.38359,
        "lon": -117.57862
      },
      "leg_dist_mi": 0.7183253100788708,
      "cum_dist_mi": 65.57886757256654
    },
    {
      "start_lat_lon": {
        "lat": 33.37919,
        "lon": -117.56733
      },
      "leg_dist_mi": 0.2608178585621689,
      "cum_dist_mi": 66.2971928826454
    },
    {
      "start_lat_lon": {
        "lat": 33.37697,
        "lon": -117.56367
      },
      "leg_dist_mi": 0.28729997335151825,
      "cum_dist_mi": 66.55801074120757
    },
    {
      "start_lat_lon": {
        "lat": 33.37423,
        "lon": -117.55992
      },
      "leg_dist_mi": 0.7708003957350691,
      "cum_dist_mi": 66.84531071455909
    },
    {
      "start_lat_lon": {
        "lat": 33.36811,
        "lon": -117.54874
      },
      "leg_dist_mi": 0.4893051624513869,
      "cum_dist_mi": 67.61611111029416
    },
    {
      "start_lat_lon": {
        "lat": 33.36374,
        "lon": -117.54206
      },
      "leg_dist_mi": 1.1703288492198543,
      "cum_dist_mi": 68.10541627274554
    },
    {
      "start_lat_lon": {
        "lat": 33.353,
        "lon": -117.52636
      },
      "leg_dist_mi": 1.3164688086928242,
      "cum_dist_mi": 69.2757451219654
    },
    {
      "start_lat_lon": {
        "lat": 33.34068,
        "lon": -117.50894
      },
      "leg_dist_mi": 1.0883597457394896,
      "cum_dist_mi": 70.59221393065822
    },
    {
      "start_lat_lon": {
        "lat": 33.33032,
        "lon": -117.49472
      },
      "leg_dist_mi": 0.5805076878186198,
      "cum_dist_mi": 71.68057367639771
    },
    {
      "start_lat_lon": {
        "lat": 33.3248,
        "lon": -117.48713
      },
      "leg_dist_mi": 0.27304187658886053,
      "cum_dist_mi": 72.26108136421634
    },
    {
      "start_lat_lon": {
        "lat": 33.32199,
        "lon": -117.4838
      },
      "leg_dist_mi": 0.27077191106575077,
      "cum_dist_mi": 72.5341232408052
    },
    {
      "start_lat_lon": {
        "lat": 33.31821,
        "lon": -117.48255
      },
      "leg_dist_mi": 0.2625177625813772,
      "cum_dist_mi": 72.80489515187095
    },
    {
      "start_lat_lon": {
        "lat": 33.31443,
        "lon": -117.48206
      },
      "leg_dist_mi": 0.23280234768211303,
      "cum_dist_mi": 73.06741291445233
    },
    {
      "start_lat_lon": {
        "lat": 33.31146,
        "lon": -117.48015
      },
      "leg_dist_mi": 0.6171964905837851,
      "cum_dist_mi": 73.30021526213444
    },
    {
      "start_lat_lon": {
        "lat": 33.30517,
        "lon": -117.47255
      },
      "leg_dist_mi": 0.5349190382850662,
      "cum_dist_mi": 73.91741175271822
    },
    {
      "start_lat_lon": {
        "lat": 33.29973,
        "lon": -117.46595
      },
      "leg_dist_mi": 0.39142131074071634,
      "cum_dist_mi": 74.45233079100329
    },
    {
      "start_lat_lon": {
        "lat": 33.29575,
        "lon": -117.46112
      },
      "leg_dist_mi": 0.2786511744241151,
      "cum_dist_mi": 74.843752101744
    },
    {
      "start_lat_lon": {
        "lat": 33.29267,
        "lon": -117.458
      },
      "leg_dist_mi": 0.6265413100917936,
      "cum_dist_mi": 75.12240327616811
    },
    {
      "start_lat_lon": {
        "lat": 33.28501,
        "lon": -117.45218
      },
      "leg_dist_mi": 0.47657274344466,
      "cum_dist_mi": 75.74894458625991
    },
    {
      "start_lat_lon": {
        "lat": 33.27918,
        "lon": -117.44776
      },
      "leg_dist_mi": 0.5924466873035237,
      "cum_dist_mi": 76.22551732970457
    },
    {
      "start_lat_lon": {
        "lat": 33.27205,
        "lon": -117.44205
      },
      "leg_dist_mi": 0.8696252155636661,
      "cum_dist_mi": 76.8179640170081
    },
    {
      "start_lat_lon": {
        "lat": 33.26349,
        "lon": -117.431
      },
      "leg_dist_mi": 0.3090798500094644,
      "cum_dist_mi": 77.68758923257177
    },
    {
      "start_lat_lon": {
        "lat": 33.25976,
        "lon": -117.42804
      },
      "leg_dist_mi": 0.6359370946146973,
      "cum_dist_mi": 77.99666908258123
    },
    {
      "start_lat_lon": {
        "lat": 33.25208,
        "lon": -117.42196
      },
      "leg_dist_mi": 0.2865350408651088,
      "cum_dist_mi": 78.63260617719594
    },
    {
      "start_lat_lon": {
        "lat": 33.24862,
        "lon": -117.41922
      },
      "leg_dist_mi": 0.2872102257360624,
      "cum_dist_mi": 78.91914121806104
    },
    {
      "start_lat_lon": {
        "lat": 33.24483,
        "lon": -117.41717
      },
      "leg_dist_mi": 0.25369451269510324,
      "cum_dist_mi": 79.2063514437971
    },
    {
      "start_lat_lon": {
        "lat": 33.24155,
        "lon": -117.41519
      },
      "leg_dist_mi": 0.36426365397113175,
      "cum_dist_mi": 79.46004595649221
    },
    {
      "start_lat_lon": {
        "lat": 33.23828,
        "lon": -117.41024
      },
      "leg_dist_mi": 0.6854051628142587,
      "cum_dist_mi": 79.82430961046335
    },
    {
      "start_lat_lon": {
        "lat": 33.23116,
        "lon": -117.40197
      },
      "leg_dist_mi": 0.782064959791088,
      "cum_dist_mi": 80.50971477327761
    },
    {
      "start_lat_lon": {
        "lat": 33.22278,
        "lon": -117.39286
      },
      "leg_dist_mi": 0.29132172222239205,
      "cum_dist_mi": 81.2917797330687
    },
    {
      "start_lat_lon": {
        "lat": 33.21879,
        "lon": -117.39122
      },
      "leg_dist_mi": 0.2819272739264248,
      "cum_dist_mi": 81.58310145529109
    },
    {
      "start_lat_lon": {
        "lat": 33.21483,
        "lon": -117.39003
      },
      "leg_dist_mi": 0.24455945594922768,
      "cum_dist_mi": 81.86502872921751
    },
    {
      "start_lat_lon": {
        "lat": 33.21164,
        "lon": -117.38819
      },
      "leg_dist_mi": 0.4219552996968387,
      "cum_dist_mi": 82.10958818516674
    },
    {
      "start_lat_lon": {
        "lat": 33.20624,
        "lon": -117.38477
      },
      "leg_dist_mi": 0.22549037252295107,
      "cum_dist_mi": 82.53154348486358
    },
    {
      "start_lat_lon": {
        "lat": 33.20385,
        "lon": -117.38211
      },
      "leg_dist_mi": 0.46543162320455234,
      "cum_dist_mi": 82.75703385738653
    },
    {
      "start_lat_lon": {
        "lat": 33.20109,
        "lon": -117.37476
      },
      "leg_dist_mi": 0.21219728658112197,
      "cum_dist_mi": 83.22246548059108
    },
    {
      "start_lat_lon": {
        "lat": 33.19983,
        "lon": -117.37141
      },
      "leg_dist_mi": 0.16748944295101878,
      "cum_dist_mi": 83.4346627671722
    },
    {
      "start_lat_lon": {
        "lat": 33.19828,
        "lon": -117.36918
      },
      "leg_dist_mi": 0.4036751391682359,
      "cum_dist_mi": 83.60215221012322
    },
    {
      "start_lat_lon": {
        "lat": 33.19351,
        "lon": -117.36514
      },
      "leg_dist_mi": 0.448843512778002,
      "cum_dist_mi": 84.00582734929147
    },
    {
      "start_lat_lon": {
        "lat": 33.18817,
        "lon": -117.36071
      },
      "leg_dist_mi": 0.8769432653532475,
      "cum_dist_mi": 84.45467086206946
    },
    {
      "start_lat_lon": {
        "lat": 33.17774,
        "lon": -117.35205
      },
      "leg_dist_mi": 0.3724331943590244,
      "cum_dist_mi": 85.33161412742271
    },
    {
      "start_lat_lon": {
        "lat": 33.1732,
        "lon": -117.34857
      },
      "leg_dist_mi": 0.5188043831917153,
      "cum_dist_mi": 85.70404732178173
    },
    {
      "start_lat_lon": {
        "lat": 33.16666,
        "lon": -117.34415
      },
      "leg_dist_mi": 1.3162537438754316,
      "cum_dist_mi": 86.22285170497345
    },
    {
      "start_lat_lon": {
        "lat": 33.14924,
        "lon": -117.3349
      },
      "leg_dist_mi": 0.19539872902488015,
      "cum_dist_mi": 87.53910544884889
    },
    {
      "start_lat_lon": {
        "lat": 33.14655,
        "lon": -117.33385
      },
      "leg_dist_mi": 0.22124704178392812,
      "cum_dist_mi": 87.73450417787376
    },
    {
      "start_lat_lon": {
        "lat": 33.14335,
        "lon": -117.33365
      },
      "leg_dist_mi": 0.3422891493086305,
      "cum_dist_mi": 87.95575121965769
    },
    {
      "start_lat_lon": {
        "lat": 33.13869,
        "lon": -117.33163
      },
      "leg_dist_mi": 1.307985957364369,
      "cum_dist_mi": 88.29804036896631
    },
    {
      "start_lat_lon": {
        "lat": 33.1216,
        "lon": -117.32187
      },
      "leg_dist_mi": 2.5130087118301727,
      "cum_dist_mi": 89.60602632633068
    },
    {
      "start_lat_lon": {
        "lat": 33.08942,
        "lon": -117.30157
      },
      "leg_dist_mi": 0.2845788225324188,
      "cum_dist_mi": 92.11903503816085
    },
    {
      "start_lat_lon": {
        "lat": 33.08579,
        "lon": -117.29924
      },
      "leg_dist_mi": 0.31614261863511967,
      "cum_dist_mi": 92.40361386069327
    },
    {
      "start_lat_lon": {
        "lat": 33.0815,
        "lon": -117.29733
      },
      "leg_dist_mi": 0.6953012624621641,
      "cum_dist_mi": 92.7197564793284
    },
    {
      "start_lat_lon": {
        "lat": 33.07174,
        "lon": -117.29437
      },
      "leg_dist_mi": 1.436640912839708,
      "cum_dist_mi": 93.41505774179056
    },
    {
      "start_lat_lon": {
        "lat": 33.05156,
        "lon": -117.28832
      },
      "leg_dist_mi": 0.4860319443838655,
      "cum_dist_mi": 94.85169865463027
    },
    {
      "start_lat_lon": {
        "lat": 33.04474,
        "lon": -117.28624
      },
      "leg_dist_mi": 0.2387116834124507,
      "cum_dist_mi": 95.33773059901414
    },
    {
      "start_lat_lon": {
        "lat": 33.04144,
        "lon": -117.28501
      },
      "leg_dist_mi": 0.18904275832080764,
      "cum_dist_mi": 95.57644228242658
    },
    {
      "start_lat_lon": {
        "lat": 33.03903,
        "lon": -117.28346
      },
      "leg_dist_mi": 0.507163918546774,
      "cum_dist_mi": 95.7654850407474
    },
    {
      "start_lat_lon": {
        "lat": 33.03263,
        "lon": -117.27916
      },
      "leg_dist_mi": 0.4570568219570784,
      "cum_dist_mi": 96.27264895929417
    },
    {
      "start_lat_lon": {
        "lat": 33.02686,
        "lon": -117.27529
      },
      "leg_dist_mi": 0.19271170567516058,
      "cum_dist_mi": 96.72970578125125
    },
    {
      "start_lat_lon": {
        "lat": 33.02428,
        "lon": -117.27402
      },
      "leg_dist_mi": 0.30075154136711274,
      "cum_dist_mi": 96.92241748692642
    },
    {
      "start_lat_lon": {
        "lat": 33.01999,
        "lon": -117.27312
      },
      "leg_dist_mi": 0.18607579797603369,
      "cum_dist_mi": 97.22316902829353
    },
    {
      "start_lat_lon": {
        "lat": 33.01744,
        "lon": -117.27208
      },
      "leg_dist_mi": 0.1854705471247504,
      "cum_dist_mi": 97.40924482626956
    },
    {
      "start_lat_lon": {
        "lat": 33.01519,
        "lon": -117.27033
      },
      "leg_dist_mi": 0.5500298014115984,
      "cum_dist_mi": 97.59471537339431
    },
    {
      "start_lat_lon": {
        "lat": 33.00942,
        "lon": -117.26378
      },
      "leg_dist_mi": 0.3997740692378866,
      "cum_dist_mi": 98.1447451748059
    },
    {
      "start_lat_lon": {
        "lat": 33.00514,
        "lon": -117.25913
      },
      "leg_dist_mi": 0.17287911661759198,
      "cum_dist_mi": 98.5445192440438
    },
    {
      "start_lat_lon": {
        "lat": 33.00284,
        "lon": -117.25795
      },
      "leg_dist_mi": 0.24388964574741515,
      "cum_dist_mi": 98.71739836066139
    },
    {
      "start_lat_lon": {
        "lat": 32.99935,
        "lon": -117.2573
      },
      "leg_dist_mi": 0.7939877921948965,
      "cum_dist_mi": 98.96128800640881
    },
    {
      "start_lat_lon": {
        "lat": 32.98795,
        "lon": -117.2555
      },
      "leg_dist_mi": 0.47677240431186835,
      "cum_dist_mi": 99.7552757986037
    },
    {
      "start_lat_lon": {
        "lat": 32.98121,
        "lon": -117.25371
      },
      "leg_dist_mi": 0.4751684193167757,
      "cum_dist_mi": 100.23204820291558
    },
    {
      "start_lat_lon": {
        "lat": 32.97465,
        "lon": -117.25123
      },
      "leg_dist_mi": 0.9263125662556311,
      "cum_dist_mi": 100.70721662223235
    },
    {
      "start_lat_lon": {
        "lat": 32.96185,
        "lon": -117.24644
      },
      "leg_dist_mi": 0.7352925270929757,
      "cum_dist_mi": 101.63352918848798
    },
    {
      "start_lat_lon": {
        "lat": 32.95138,
        "lon": -117.24412
      },
      "leg_dist_mi": 1.0474932506804593,
      "cum_dist_mi": 102.36882171558096
    },
    {
      "start_lat_lon": {
        "lat": 32.93635,
        "lon": -117.24166
      },
      "leg_dist_mi": 0.37965966435009757,
      "cum_dist_mi": 103.41631496626142
    },
    {
      "start_lat_lon": {
        "lat": 32.93087,
        "lon": -117.24112
      },
      "leg_dist_mi": 0.266548378171323,
      "cum_dist_mi": 103.79597463061152
    },
    {
      "start_lat_lon": {
        "lat": 32.9271,
        "lon": -117.24013
      },
      "leg_dist_mi": 0.47723149157125827,
      "cum_dist_mi": 104.06252300878285
    },
    {
      "start_lat_lon": {
        "lat": 32.9206,
        "lon": -117.23733
      },
      "leg_dist_mi": 0.4162084851057182,
      "cum_dist_mi": 104.5397545003541
    },
    {
      "start_lat_lon": {
        "lat": 32.91617,
        "lon": -117.23246
      },
      "leg_dist_mi": 0.16129454972256382,
      "cum_dist_mi": 104.95596298545982
    },
    {
      "start_lat_lon": {
        "lat": 32.91444,
        "lon": -117.23059
      },
      "leg_dist_mi": 0.2808416636603221,
      "cum_dist_mi": 105.11725753518239
    },
    {
      "start_lat_lon": {
        "lat": 32.91086,
        "lon": -117.22829
      },
      "leg_dist_mi": 0.2546015944639265,
      "cum_dist_mi": 105.39809919884271
    },
    {
      "start_lat_lon": {
        "lat": 32.90759,
        "lon": -117.22626
      },
      "leg_dist_mi": 0.26729540036095756,
      "cum_dist_mi": 105.65270079330664
    },
    {
      "start_lat_lon": {
        "lat": 32.90395,
        "lon": -117.22469
      },
      "leg_dist_mi": 0.16248911249889592,
      "cum_dist_mi": 105.9199961936676
    },
    {
      "start_lat_lon": {
        "lat": 32.9016,
        "lon": -117.22454
      },
      "leg_dist_mi": 0.19183855080719,
      "cum_dist_mi": 106.08248530616649
    },
    {
      "start_lat_lon": {
        "lat": 32.89889,
        "lon": -117.22527
      },
      "leg_dist_mi": 0.532368356162503,
      "cum_dist_mi": 106.27432385697368
    },
    {
      "start_lat_lon": {
        "lat": 32.8914,
        "lon": -117.22745
      },
      "leg_dist_mi": 0.5189737465300942,
      "cum_dist_mi": 106.80669221313619
    },
    {
      "start_lat_lon": {
        "lat": 32.88391,
        "lon": -117.2282
      },
      "leg_dist_mi": 1.3315672941287764,
      "cum_dist_mi": 107.32566595966628
    },
    {
      "start_lat_lon": {
        "lat": 32.86469,
        "lon": -117.23009
      },
      "leg_dist_mi": 0.3615347118645927,
      "cum_dist_mi": 108.65723325379506
    },
    {
      "start_lat_lon": {
        "lat": 32.85947,
        "lon": -117.23058
      },
      "leg_dist_mi": 0.2700411714744272,
      "cum_dist_mi": 109.01876796565965
    },
    {
      "start_lat_lon": {
        "lat": 32.85561,
        "lon": -117.23133
      },
      "leg_dist_mi": 0.523181415126747,
      "cum_dist_mi": 109.28880913713408
    },
    {
      "start_lat_lon": {
        "lat": 32.84894,
        "lon": -117.23561
      },
      "leg_dist_mi": 0.2159327243921154,
      "cum_dist_mi": 109.81199055226082
    },
    {
      "start_lat_lon": {
        "lat": 32.84587,
        "lon": -117.23632
      },
      "leg_dist_mi": 0.312783476909431,
      "cum_dist_mi": 110.02792327665294
    },
    {
      "start_lat_lon": {
        "lat": 32.84134,
        "lon": -117.23636
      },
      "leg_dist_mi": 0.44511408932665986,
      "cum_dist_mi": 110.34070675356237
    },
    {
      "start_lat_lon": {
        "lat": 32.83529,
        "lon": -117.23371
      },
      "leg_dist_mi": 0.1784670941398369,
      "cum_dist_mi": 110.78582084288904
    },
    {
      "start_lat_lon": {
        "lat": 32.83276,
        "lon": -117.23308
      },
      "leg_dist_mi": 0.3224599915819923,
      "cum_dist_mi": 110.96428793702887
    },
    {
      "start_lat_lon": {
        "lat": 32.82809,
        "lon": -117.23302
      },
      "leg_dist_mi": 0.2075962052197227,
      "cum_dist_mi": 111.28674792861086
    },
    {
      "start_lat_lon": {
        "lat": 32.82518,
        "lon": -117.23212
      },
      "leg_dist_mi": 0.25398891546026514,
      "cum_dist_mi": 111.4943441338306
    },
    {
      "start_lat_lon": {
        "lat": 32.82219,
        "lon": -117.22957
      },
      "leg_dist_mi": 0.7590958865548093,
      "cum_dist_mi": 111.74833304929086
    },
    {
      "start_lat_lon": {
        "lat": 32.81359,
        "lon": -117.22142
      },
      "leg_dist_mi": 0.9594504883337509,
      "cum_dist_mi": 112.50742893584567
    },
    {
      "start_lat_lon": {
        "lat": 32.80189,
        "lon": -117.2125
      },
      "leg_dist_mi": 0.4360502135172832,
      "cum_dist_mi": 113.46687942417942
    },
    {
      "start_lat_lon": {
        "lat": 32.79618,
        "lon": -117.20929
      },
      "leg_dist_mi": 0.321565504890639,
      "cum_dist_mi": 113.9029296376967
    },
    {
      "start_lat_lon": {
        "lat": 32.79179,
        "lon": -117.20744
      },
      "leg_dist_mi": 0.225071588879046,
      "cum_dist_mi": 114.22449514258734
    },
    {
      "start_lat_lon": {
        "lat": 32.78854,
        "lon": -117.20714
      },
      "leg_dist_mi": 0.3056677434315112,
      "cum_dist_mi": 114.44956673146639
    },
    {
      "start_lat_lon": {
        "lat": 32.78415,
        "lon": -117.20782
      },
      "leg_dist_mi": 0.44147065349546094,
      "cum_dist_mi": 114.7552344748979
    },
    {
      "start_lat_lon": {
        "lat": 32.7778,
        "lon": -117.20871
      },
      "leg_dist_mi": 0.17372222967780726,
      "cum_dist_mi": 115.19670512839336
    },
    {
      "start_lat_lon": {
        "lat": 32.77533,
        "lon": -117.20814
      },
      "leg_dist_mi": 0.5459580422230226,
      "cum_dist_mi": 115.37042735807117
    },
    {
      "start_lat_lon": {
        "lat": 32.7676,
        "lon": -117.20616
      },
      "leg_dist_mi": 0.3996392715844963,
      "cum_dist_mi": 115.91638540029419
    },
    {
      "start_lat_lon": {
        "lat": 32.76194,
        "lon": -117.20472
      },
      "leg_dist_mi": 0.32503700128034424,
      "cum_dist_mi": 116.31602467187868
    },
    {
      "start_lat_lon": {
        "lat": 32.75734,
        "lon": -117.20353
      },
      "leg_dist_mi": 0.1400419596226423,
      "cum_dist_mi": 116.64106167315903
    },
    {
      "start_lat_lon": {
        "lat": 32.75551,
        "lon": -117.20249
      },
      "leg_dist_mi": 0.12277830073345365,
      "cum_dist_mi": 116.78110363278167
    },
    {
      "start_lat_lon": {
        "lat": 32.75424,
        "lon": -117.20101
      },
      "leg_dist_mi": 0.33090545059347853,
      "cum_dist_mi": 116.90388193351512
    },
    {
      "start_lat_lon": {
        "lat": 32.75081,
        "lon": -117.19703
      },
      "leg_dist_mi": 0.2174264327881842,
      "cum_dist_mi": 117.2347873841086
    },
    {
      "start_lat_lon": {
        "lat": 32.7484,
        "lon": -117.19462
      },
      "leg_dist_mi": 0.1961674376109846,
      "cum_dist_mi": 117.45221381689679
    },
    {
      "start_lat_lon": {
        "lat": 32.74675,
        "lon": -117.19187
      },
      "leg_dist_mi": 0.6368975182724034,
      "cum_dist_mi": 117.64838125450777
    },
    {
      "start_lat_lon": {
        "lat": 32.74229,
        "lon": -117.18227
      },
      "leg_dist_mi": 0.16383428348419163,
      "cum_dist_mi": 118.28527877278017
    },
    {
      "start_lat_lon": {
        "lat": 32.74094,
        "lon": -117.17995
      },
      "leg_dist_mi": 0.21414348527472832,
      "cum_dist_mi": 118.44911305626437
    },
    {
      "start_lat_lon": {
        "lat": 32.73847,
        "lon": -117.17772
      },
      "leg_dist_mi": 0.6315397749494565,
      "cum_dist_mi": 118.6632565415391
    },
    {
      "start_lat_lon": {
        "lat": 32.7311,
        "lon": -117.17128
      },
      "leg_dist_mi": 0.3738214936907307,
      "cum_dist_mi": 119.29479631648856
    },
    {
      "start_lat_lon": {
        "lat": 32.72667,
        "lon": -117.16758
      },
      "leg_dist_mi": 0.20105024695969634,
      "cum_dist_mi": 119.66861781017928
    },
    {
      "start_lat_lon": {
        "lat": 32.72433,
        "lon": -117.16552
      },
      "leg_dist_mi": 0.15943878808665296,
      "cum_dist_mi": 119.86966805713898
    },
    {
      "start_lat_lon": {
        "lat": 32.72231,
        "lon": -117.16419
      },
      "leg_dist_mi": 0.06667201579401413,
      "cum_dist_mi": 120.02910684522563
    },
    {
      "start_lat_lon": {
        "lat": 32.72192,
        "lon": -117.16314
      },
      "leg_dist_mi": 0.11738855556477866,
      "cum_dist_mi": 120.09577886101964
    },
    {
      "start_lat_lon": {
        "lat": 32.72197,
        "lon": -117.16112
      },
      "leg_dist_mi": 0.15604653376827857,
      "cum_dist_mi": 120.21316741658441
    },
    {
      "start_lat_lon": {
        "lat": 32.71971,
        "lon": -117.1611
      },
      "leg_dist_mi": 0.27479999633137364,
      "cum_dist_mi": 120.36921395035269
    },
    {
      "start_lat_lon": {
        "lat": 32.71573,
        "lon": -117.1611
      },
      "leg_dist_mi": 0.0,
      "cum_dist_mi": 120.64401394668405
    }
  ]
}